Workbook

Sheet README
B2: IT General Controls (ITGC) & User Access Compliance Audit
B3: A self-contained Excel audit workbook demonstrating access-provisioning, deprovisioning, segregation-of-duties, and recertification testing.
B5: Purpose
B6: Simulates a mid-size company's IT access environment (5 business systems, 14 roles, 50 employees, 174 access grants, 118 recertification records) with deliberately embedded ITGC control failures. Every formula in the workbook re-performs a specific audit test an IT/ITGC auditor runs during a SOX or ISO 27001 access review.
B8: Control Objectives Tested
B9: 1) Timely deprovisioning of terminated users (Access_Termination reconciliation) 2) Segregation of Duties (SoD) — no single identity holds two conflicting roles 3) Access provisioned only with documented approval 4) Periodic access recertification completed on schedule, especially for privileged/admin access
B11: How the workbook is wired
B12: HR_Employees, Access_Grants, SoD_Conflict_Matrix and Recertifications are the SOURCE DATA (raw logs, as you would export from HRIS / IAM tooling). Audit_Testing is the AUDIT ENGINE — one row per access grant, entirely formula-driven, that reconciles across the source sheets and raises an exception with a root-cause category. Dashboard aggregates Audit_Testing and Recertifications into exception-rate summaries by Department / System / Reviewer, ready to also drive a native Excel PivotTable (Insert > PivotTable > source = the 'AuditTesting' table) since the underlying range is a proper Excel Table.
B14: Why no VBA / macros / ML
B15: Every flag is a native, auditable Excel formula (INDEX/MATCH, COUNTIFS, nested IF/AND/OR, IFERROR). No macros, no black-box scoring — every number in this workbook can be traced back to a cell you can open and explain line by line, which is exactly what a reviewer or interview panel will ask you to do.
B17: Data disclaimer
B18: All employee names, dates and IDs are synthetically generated (Python, seed=42) for demonstration purposes only. 'Today' for aging/recency calculations is fixed conceptually at 2026-09-18 (TODAY() is used live in formulas, so aging figures will continue to update as you open the file after that date).
B20: Workbook map
B21: README | C21: This page.
B22: HR_Employees | C22: HR master data — hire/termination dates (source of truth for deprovisioning testing).
B23: SoD_Conflict_Matrix | C23: The 6 role-pair conflict rules tested (a real company's SoD ruleset would run to hundreds of rows; this is a representative subset).
B24: Access_Grants | C24: Raw IAM access-provisioning log — every grant of a role to a user, its approver, and its current status.
B25: Recertifications | C25: Periodic access review log — due dates, reviewers, completion dates and outcomes.
B26: Audit_Testing | C26: THE AUDIT ENGINE. One row per access grant with 4 independent formula-driven tests + an overall exception verdict and root-cause category.
B27: Dashboard | C27: Exception-rate summaries by Department, System and Reviewer, plus root-cause mix. Conditional formatting highlights hot spots.
B28: Findings_Memo | C28: Written audit findings memo: condition / criteria / cause / effect / recommendation for each control gap, addressed to the Audit Committee.

Sheet HR_Employees
A1: EmployeeID | B1: Name | C1: Department | D1: JobTitle | E1: HireDate | F1: TerminationDate | G1: Manager | H1: EmploymentStatus
A2: E001 | B2: Sophia Chen | C2: IT Operations | D2: Clerk | E2: 44469 | G2: MGR-02 | H2: =IF(F2="","Active","Terminated") -> Active
A3: E002 | B3: Peter Okafor | C3: HR | D3: Manager | E3: 43596 | F3: 45881 | G3: MGR-04 | H3: =IF(F3="","Active","Terminated") -> Terminated
A4: E003 | B4: Youssef Chen | C4: Procurement | D4: Specialist | E4: 44280 | G4: MGR-09 | H4: =IF(F4="","Active","Terminated") -> Active
A5: E004 | B5: Omar Khan | C5: IT Operations | D5: Clerk | E5: 43492 | G5: MGR-03 | H5: =IF(F5="","Active","Terminated") -> Active
A6: E005 | B6: Olivia Andersson | C6: IT Operations | D6: Analyst | E6: 44102 | G6: MGR-06 | H6: =IF(F6="","Active","Terminated") -> Active
A7: E006 | B7: Fatima Santos | C7: Accounts Payable | D7: Associate | E7: 44936 | G7: MGR-10 | H7: =IF(F7="","Active","Terminated") -> Active
A8: E007 | B8: Wei Petrov | C8: Customer Service | D8: Manager | E8: 45662 | F8: 46049 | G8: MGR-02 | H8: =IF(F8="","Active","Terminated") -> Terminated
A9: E008 | B9: Diego Ferreira | C9: Treasury | D9: Clerk | E9: 44253 | G9: MGR-01 | H9: =IF(F9="","Active","Terminated") -> Active
A10: E009 | B10: Omar Diallo | C10: IT Operations | D10: Specialist | E10: 43792 | G10: MGR-02 | H10: =IF(F10="","Active","Terminated") -> Active
A11: E010 | B11: Ingrid Khan | C11: Treasury | D11: Clerk | E11: 44132 | G11: MGR-04 | H11: =IF(F11="","Active","Terminated") -> Active
A12: E011 | B12: Ingrid Reyes | C12: Accounts Payable | D12: Senior Analyst | E12: 44166 | G12: MGR-04 | H12: =IF(F12="","Active","Terminated") -> Active
A13: E012 | B13: Zara Santos | C13: IT Operations | D13: Analyst | E13: 45747 | G13: MGR-06 | H13: =IF(F13="","Active","Terminated") -> Active
A14: E013 | B14: Omar Ferreira | C14: Finance | D14: Senior Analyst | E14: 44758 | G14: MGR-02 | H14: =IF(F14="","Active","Terminated") -> Active
A15: E014 | B15: Raj Osei | C15: Treasury | D15: Clerk | E15: 44336 | G15: MGR-07 | H15: =IF(F15="","Active","Terminated") -> Active
A16: E015 | B16: Zara Silva | C16: IT Operations | D16: Manager | E16: 44037 | G16: MGR-09 | H16: =IF(F16="","Active","Terminated") -> Active
A17: E016 | B17: Tariq Petrov | C17: HR | D17: Manager | E17: 45101 | G17: MGR-03 | H17: =IF(F17="","Active","Terminated") -> Active
A18: E017 | B18: Isabel Okafor | C18: Finance | D18: Manager | E18: 43915 | F18: 45821 | G18: MGR-07 | H18: =IF(F18="","Active","Terminated") -> Terminated
A19: E018 | B19: Carlos Santos | C19: HR | D19: Analyst | E19: 45383 | G19: MGR-09 | H19: =IF(F19="","Active","Terminated") -> Active
A20: E019 | B20: Sophia Abara | C20: Procurement | D20: Analyst | E20: 44558 | G20: MGR-06 | H20: =IF(F20="","Active","Terminated") -> Active
A21: E020 | B21: Diego Ivanov | C21: Payroll | D21: Senior Analyst | E21: 45324 | F21: 45927 | G21: MGR-09 | H21: =IF(F21="","Active","Terminated") -> Terminated
A22: E021 | B22: Kofi Braga | C22: Accounts Payable | D22: Manager | E22: 44688 | G22: MGR-09 | H22: =IF(F22="","Active","Terminated") -> Active
A23: E022 | B23: Rahul Silva | C23: Treasury | D23: Analyst | E23: 44127 | G23: MGR-09 | H23: =IF(F23="","Active","Terminated") -> Active
A24: E023 | B24: Youssef Andersson | C24: Customer Service | D24: Senior Analyst | E24: 43545 | F24: 46029 | G24: MGR-05 | H24: =IF(F24="","Active","Terminated") -> Terminated
A25: E024 | B25: Priya Rossi | C25: Accounts Payable | D25: Manager | E25: 43816 | G25: MGR-02 | H25: =IF(F25="","Active","Terminated") -> Active
A26: E025 | B26: Kenji Silva | C26: Customer Service | D26: Specialist | E26: 45717 | F26: 46257 | G26: MGR-10 | H26: =IF(F26="","Active","Terminated") -> Terminated
A27: E026 | B27: Grace Braga | C27: Procurement | D27: Clerk | E27: 44289 | G27: MGR-07 | H27: =IF(F27="","Active","Terminated") -> Active
A28: E027 | B28: Laura Khan | C28: Procurement | D28: Associate | E28: 45315 | F28: 45888 | G28: MGR-02 | H28: =IF(F28="","Active","Terminated") -> Terminated
A29: E028 | B29: Maria Haruki | C29: Procurement | D29: Analyst | E29: 44408 | G29: MGR-01 | H29: =IF(F29="","Active","Terminated") -> Active
A30: E029 | B30: Carlos Osei | C30: Finance | D30: Clerk | E30: 44819 | F30: 45901 | G30: MGR-05 | H30: =IF(F30="","Active","Terminated") -> Terminated
A31: E030 | B31: Isabel Nakamura | C31: Procurement | D31: Manager | E31: 44007 | G31: MGR-10 | H31: =IF(F31="","Active","Terminated") -> Active
A32: E031 | B32: Adam Rossi | C32: Customer Service | D32: Clerk | E32: 45133 | G32: MGR-02 | H32: =IF(F32="","Active","Terminated") -> Active
A33: E032 | B33: Olivia Kim | C33: HR | D33: Clerk | E33: 45149 | G33: MGR-01 | H33: =IF(F33="","Active","Terminated") -> Active
A34: E033 | B34: Liam Garcia | C34: HR | D34: Senior Analyst | E34: 44855 | G34: MGR-02 | H34: =IF(F34="","Active","Terminated") -> Active
A35: E034 | B35: Rahul Nakamura | C35: Procurement | D35: Specialist | E35: 45303 | F35: 45845 | G35: MGR-05 | H35: =IF(F35="","Active","Terminated") -> Terminated
A36: E035 | B36: Chloe Kowalski | C36: Accounts Payable | D36: Analyst | E36: 45281 | G36: MGR-09 | H36: =IF(F36="","Active","Terminated") -> Active
A37: E036 | B37: Priya Schmidt | C37: Procurement | D37: Senior Analyst | E37: 43526 | G37: MGR-04 | H37: =IF(F37="","Active","Terminated") -> Active
A38: E037 | B38: Sanjay Dubois | C38: Customer Service | D38: Senior Analyst | E38: 44341 | G38: MGR-01 | H38: =IF(F38="","Active","Terminated") -> Active
A39: E038 | B39: Victor Chen | C39: HR | D39: Associate | E39: 44552 | G39: MGR-08 | H39: =IF(F39="","Active","Terminated") -> Active
A40: E039 | B40: Olivia Reyes | C40: Procurement | D40: Analyst | E40: 45459 | F40: 45961 | G40: MGR-04 | H40: =IF(F40="","Active","Terminated") -> Terminated
A41: E040 | B41: Emma Petrov | C41: Procurement | D41: Analyst | E41: 43715 | G41: MGR-01 | H41: =IF(F41="","Active","Terminated") -> Active
A42: E041 | B42: Emma Dubois | C42: Procurement | D42: Senior Analyst | E42: 45641 | F42: 46178 | G42: MGR-02 | H42: =IF(F42="","Active","Terminated") -> Terminated
A43: E042 | B43: Carlos Lopez | C43: Accounts Payable | D43: Senior Analyst | E43: 44429 | G43: MGR-10 | H43: =IF(F43="","Active","Terminated") -> Active
A44: E043 | B44: Emma Lopez | C44: Finance | D44: Manager | E44: 43801 | G44: MGR-10 | H44: =IF(F44="","Active","Terminated") -> Active
A45: E044 | B45: Hana Andersson | C45: IT Operations | D45: Senior Analyst | E45: 44302 | G45: MGR-06 | H45: =IF(F45="","Active","Terminated") -> Active
A46: E045 | B46: Tariq Santos | C46: Payroll | D46: Analyst | E46: 44694 | G46: MGR-02 | H46: =IF(F46="","Active","Terminated") -> Active
A47: E046 | B47: Zara Lopez | C47: Accounts Payable | D47: Associate | E47: 43766 | G47: MGR-09 | H47: =IF(F47="","Active","Terminated") -> Active
A48: E047 | B48: Kenji Braga | C48: Treasury | D48: Associate | E48: 43747 | G48: MGR-06 | H48: =IF(F48="","Active","Terminated") -> Active
A49: E048 | B49: Noah Khan | C49: Procurement | D49: Analyst | E49: 44705 | G49: MGR-09 | H49: =IF(F49="","Active","Terminated") -> Active
A50: E049 | B50: Ana Novak | C50: Accounts Payable | D50: Clerk | E50: 44016 | G50: MGR-02 | H50: =IF(F50="","Active","Terminated") -> Active
A51: E050 | B51: Ana Silva | C51: IT Operations | D51: Senior Analyst | E51: 44620 | G51: MGR-06 | H51: =IF(F51="","Active","Terminated") -> Active

Sheet SoD_Conflict_Matrix
A1: RuleID | B1: RoleA_ID | C1: RoleA_Name | D1: RoleB_ID | E1: RoleB_Name | F1: ConflictRationale
A2: SOD-01 | B2: R01 | C2: AP Invoice Entry | D2: R02 | E2: AP Payment Approval | F2: Same user can enter AND approve AP invoices/payments (fictitious vendor payment risk)
A3: SOD-02 | B3: R03 | C3: Vendor Master Maintenance | D3: R02 | E3: AP Payment Approval | F3: Same user can create/edit vendor master AND approve payments (ghost vendor fraud risk)
A4: SOD-03 | B4: R04 | C4: GL Journal Posting | D4: R05 | E4: GL Journal Approval | F4: Same user can post AND approve GL journal entries (unauthorized/erroneous entries risk)
A5: SOD-04 | B5: R06 | C5: Payroll Data Entry | D5: R07 | E5: Payroll Approval / Release | F5: Same user can enter AND approve/release payroll (ghost employee / inflated pay risk)
A6: SOD-05 | B6: R11 | C6: Sales Order Entry | D6: R12 | E6: Sales Credit Memo Approval | F6: Same user can enter sales orders AND approve credit memos (revenue manipulation risk)
A7: SOD-06 | B7: R13 | C7: Wire Initiation | D7: R14 | E7: Wire Approval / Release | F7: Same user can initiate AND approve/release wire transfers (unauthorized funds transfer risk)

Sheet Access_Grants
A1: GrantID | B1: EmployeeID | C1: EmployeeName | D1: Department | E1: SystemID | F1: RoleID | G1: RoleName | H1: AccessLevel | I1: GrantDate | J1: ApprovedBy | K1: ApprovalDocRef | L1: Status | M1: RevokeDate
A2: AG-0001 | B2: E001 | C2: Sophia Chen | D2: IT Operations | E2: SYS-AD | F2: R09 | G2: Standard Network User | H2: Read | I2: 45031 | J2: MGR-02 | K2: CHG-93136 | L2: Active
A3: AG-0002 | B3: E001 | C3: Sophia Chen | D3: IT Operations | E3: SYS-HRIS | F3: R08 | G3: Employee Master Read-Only | H3: Read | I3: 44934 | J3: MGR-06 | K3: CHG-27146 | L3: Active
A4: AG-0003 | B4: E001 | C4: Sophia Chen | D4: IT Operations | E4: SYS-AD | F4: R10 | G4: Domain Administrator | H4: Admin | I4: 45831 | J4: MGR-09 | K4: CHG-66057 | L4: Active
A5: AG-0004 | B5: E002 | C5: Peter Okafor | D5: HR | E5: SYS-AD | F5: R09 | G5: Standard Network User | H5: Read | I5: 44964 | K5: CHG-26704 | L5: Revoked | M5: 45882
A6: AG-0005 | B6: E002 | C6: Peter Okafor | D6: HR | E6: SYS-HRIS | F6: R07 | G6: Payroll Approval / Release | H6: Admin | I6: 45018 | J6: MGR-04 | K6: CHG-99399 | L6: Active
A7: AG-0006 | B7: E002 | C7: Peter Okafor | D7: HR | E7: SYS-HRIS | F7: R06 | G7: Payroll Data Entry | H7: Write | I7: 45070 | J7: MGR-07 | K7: CHG-91351 | L7: Revoked | M7: 45883
A8: AG-0007 | B8: E002 | C8: Peter Okafor | D8: HR | E8: SYS-HRIS | F8: R08 | G8: Employee Master Read-Only | H8: Read | I8: 44968 | J8: MGR-03 | L8: Active
A9: AG-0008 | B9: E003 | C9: Youssef Chen | D9: Procurement | E9: SYS-AD | F9: R09 | G9: Standard Network User | H9: Read | I9: 45037 | J9: MGR-07 | K9: CHG-15075 | L9: Active
A10: AG-0009 | B10: E003 | C10: Youssef Chen | D10: Procurement | E10: SYS-ERP | F10: R03 | G10: Vendor Master Maintenance | H10: Write | I10: 45763 | J10: MGR-08 | K10: CHG-55830 | L10: Active
A11: AG-0010 | B11: E003 | C11: Youssef Chen | D11: Procurement | E11: SYS-ERP | F11: R01 | G11: AP Invoice Entry | H11: Write | I11: 45160 | J11: MGR-04 | K11: CHG-13101 | L11: Active
A12: AG-0011 | B12: E004 | C12: Omar Khan | D12: IT Operations | E12: SYS-AD | F12: R10 | G12: Domain Administrator | H12: Admin | I12: 44978 | J12: System Auto-Provision | K12: CHG-80282 | L12: Revoked | M12: 45512
A13: AG-0012 | B13: E004 | C13: Omar Khan | D13: IT Operations | E13: SYS-HRIS | F13: R08 | G13: Employee Master Read-Only | H13: Read | I13: 44949 | J13: MGR-10 | L13: Active
A14: AG-0013 | B14: E004 | C14: Omar Khan | D14: IT Operations | E14: SYS-AD | F14: R09 | G14: Standard Network User | H14: Read | I14: 44967 | J14: MGR-07 | K14: CHG-89457 | L14: Active
A15: AG-0014 | B15: E005 | C15: Olivia Andersson | D15: IT Operations | E15: SYS-AD | F15: R10 | G15: Domain Administrator | H15: Admin | I15: 44928 | J15: MGR-09 | K15: CHG-80575 | L15: Active
A16: AG-0015 | B16: E005 | C16: Olivia Andersson | D16: IT Operations | E16: SYS-HRIS | F16: R08 | G16: Employee Master Read-Only | H16: Read | I16: 45128 | J16: MGR-06 | L16: Active
A17: AG-0016 | B17: E005 | C17: Olivia Andersson | D17: IT Operations | E17: SYS-AD | F17: R09 | G17: Standard Network User | H17: Read | I17: 45248 | J17: System Auto-Provision | K17: CHG-26334 | L17: Active
A18: AG-0017 | B18: E006 | C18: Fatima Santos | D18: Accounts Payable | E18: SYS-ERP | F18: R03 | G18: Vendor Master Maintenance | H18: Write | I18: 46071 | J18: MGR-03 | K18: CHG-35144 | L18: Active
A19: AG-0018 | B19: E006 | C19: Fatima Santos | D19: Accounts Payable | E19: SYS-HRIS | F19: R08 | G19: Employee Master Read-Only | H19: Read | I19: 45292 | J19: MGR-10 | K19: CHG-84593 | L19: Active
A20: AG-0019 | B20: E006 | C20: Fatima Santos | D20: Accounts Payable | E20: SYS-AD | F20: R09 | G20: Standard Network User | H20: Read | I20: 44936 | J20: MGR-05 | K20: CHG-47606 | L20: Active
A21: AG-0020 | B21: E007 | C21: Wei Petrov | D21: Customer Service | E21: SYS-HRIS | F21: R08 | G21: Employee Master Read-Only | H21: Read | I21: 45880 | J21: MGR-09 | K21: CHG-72021 | L21: Revoked | M21: 46054
A22: AG-0021 | B22: E007 | C22: Wei Petrov | D22: Customer Service | E22: SYS-CRM | F22: R11 | G22: Sales Order Entry | H22: Write | I22: 45835 | J22: System Auto-Provision | K22: CHG-21114 | L22: Revoked | M22: 46053
A23: AG-0022 | B23: E007 | C23: Wei Petrov | D23: Customer Service | E23: SYS-AD | F23: R09 | G23: Standard Network User | H23: Read | I23: 46005 | J23: MGR-02 | K23: CHG-40784 | L23: Active
A24: AG-0023 | B24: E008 | C24: Diego Ferreira | D24: Treasury | E24: SYS-BANK | F24: R14 | G24: Wire Approval / Release | H24: Admin | I24: 45552 | J24: MGR-02 | K24: CHG-69692 | L24: Active
A25: AG-0024 | B25: E008 | C25: Diego Ferreira | D25: Treasury | E25: SYS-AD | F25: R09 | G25: Standard Network User | H25: Read | I25: 45126 | J25: MGR-07 | K25: CHG-74799 | L25: Active
A26: AG-0025 | B26: E008 | C26: Diego Ferreira | D26: Treasury | E26: SYS-HRIS | F26: R06 | G26: Payroll Data Entry | H26: Write | I26: 45631 | J26: MGR-01 | K26: CHG-23970 | L26: Active
A27: AG-0026 | B27: E008 | C27: Diego Ferreira | D27: Treasury | E27: SYS-HRIS | F27: R07 | G27: Payroll Approval / Release | H27: Admin | I27: 45750 | K27: CHG-70889 | L27: Active
A28: AG-0027 | B28: E009 | C28: Omar Diallo | D28: IT Operations | E28: SYS-AD | F28: R10 | G28: Domain Administrator | H28: Admin | I28: 45153 | J28: MGR-10 | K28: CHG-76162 | L28: Active
A29: AG-0028 | B29: E009 | C29: Omar Diallo | D29: IT Operations | E29: SYS-HRIS | F29: R08 | G29: Employee Master Read-Only | H29: Read | I29: 45155 | J29: MGR-03 | K29: CHG-72216 | L29: Active
A30: AG-0029 | B30: E009 | C30: Omar Diallo | D30: IT Operations | E30: SYS-AD | F30: R09 | G30: Standard Network User | H30: Read | I30: 45253 | J30: MGR-05 | K30: CHG-78327 | L30: Active
A31: AG-0030 | B31: E010 | C31: Ingrid Khan | D31: Treasury | E31: SYS-AD | F31: R09 | G31: Standard Network User | H31: Read | I31: 45270 | K31: CHG-80798 | L31: Active
A32: AG-0031 | B32: E010 | C32: Ingrid Khan | D32: Treasury | E32: SYS-BANK | F32: R13 | G32: Wire Initiation | H32: Write | I32: 45083 | J32: MGR-04 | K32: CHG-18418 | L32: Active
A33: AG-0032 | B33: E010 | C33: Ingrid Khan | D33: Treasury | E33: SYS-BANK | F33: R14 | G33: Wire Approval / Release | H33: Admin | I33: 45404 | J33: MGR-07 | K33: CHG-18161 | L33: Active
A34: AG-0033 | B34: E011 | C34: Ingrid Reyes | D34: Accounts Payable | E34: SYS-ERP | F34: R01 | G34: AP Invoice Entry | H34: Write | I34: 45232 | J34: MGR-07 | K34: CHG-64921 | L34: Active
A35: AG-0034 | B35: E011 | C35: Ingrid Reyes | D35: Accounts Payable | E35: SYS-ERP | F35: R03 | G35: Vendor Master Maintenance | H35: Write | I35: 45544 | J35: MGR-04 | K35: CHG-73993 | L35: Active
A36: AG-0035 | B36: E011 | C36: Ingrid Reyes | D36: Accounts Payable | E36: SYS-AD | F36: R09 | G36: Standard Network User | H36: Read | I36: 44956 | J36: MGR-07 | K36: CHG-54057 | L36: Active
A37: AG-0036 | B37: E011 | C37: Ingrid Reyes | D37: Accounts Payable | E37: SYS-ERP | F37: R02 | G37: AP Payment Approval | H37: Write | I37: 45096 | J37: MGR-08 | K37: CHG-26728 | L37: Active
A38: AG-0037 | B38: E012 | C38: Zara Santos | D38: IT Operations | E38: SYS-AD | F38: R09 | G38: Standard Network User | H38: Read | I38: 45885 | K38: CHG-33819 | L38: Active
A39: AG-0038 | B39: E012 | C39: Zara Santos | D39: IT Operations | E39: SYS-AD | F39: R10 | G39: Domain Administrator | H39: Admin | I39: 46081 | J39: MGR-06 | K39: CHG-59692 | L39: Active
A40: AG-0039 | B40: E012 | C40: Zara Santos | D40: IT Operations | E40: SYS-HRIS | F40: R08 | G40: Employee Master Read-Only | H40: Read | I40: 46178 | J40: MGR-05 | K40: CHG-20735 | L40: Active
A41: AG-0040 | B41: E013 | C41: Omar Ferreira | D41: Finance | E41: SYS-HRIS | F41: R08 | G41: Employee Master Read-Only | H41: Read | I41: 45009 | J41: MGR-01 | K41: CHG-42411 | L41: Revoked | M41: 45321
A42: AG-0041 | B42: E013 | C42: Omar Ferreira | D42: Finance | E42: SYS-ERP | F42: R05 | G42: GL Journal Approval | H42: Admin | I42: 45415 | J42: MGR-03 | K42: CHG-72070 | L42: Active
A43: AG-0042 | B43: E014 | C43: Raj Osei | D43: Treasury | E43: SYS-HRIS | F43: R08 | G43: Employee Master Read-Only | H43: Read | I43: 45304 | J43: MGR-03 | K43: CHG-89415 | L43: Active
A44: AG-0043 | B44: E014 | C44: Raj Osei | D44: Treasury | E44: SYS-BANK | F44: R13 | G44: Wire Initiation | H44: Write | I44: 45044 | K44: CHG-50768 | L44: Active
A45: AG-0044 | B45: E015 | C45: Zara Silva | D45: IT Operations | E45: SYS-HRIS | F45: R08 | G45: Employee Master Read-Only | H45: Read | I45: 45175 | J45: MGR-02 | K45: CHG-49529 | L45: Active
A46: AG-0045 | B46: E015 | C46: Zara Silva | D46: IT Operations | E46: SYS-AD | F46: R09 | G46: Standard Network User | H46: Read | I46: 45050 | J46: MGR-10 | K46: CHG-15383 | L46: Active
A47: AG-0046 | B47: E015 | C47: Zara Silva | D47: IT Operations | E47: SYS-AD | F47: R10 | G47: Domain Administrator | H47: Admin | I47: 45306 | J47: MGR-02 | K47: CHG-76317 | L47: Revoked | M47: 45736
A48: AG-0047 | B48: E015 | C48: Zara Silva | D48: IT Operations | E48: SYS-BANK | F48: R13 | G48: Wire Initiation | H48: Write | I48: 45428 | J48: MGR-02 | K48: CHG-66822 | L48: Active
A49: AG-0048 | B49: E015 | C49: Zara Silva | D49: IT Operations | E49: SYS-BANK | F49: R14 | G49: Wire Approval / Release | H49: Admin | I49: 45397 | J49: MGR-03 | K49: CHG-67080 | L49: Active
A50: AG-0049 | B50: E016 | C50: Tariq Petrov | D50: HR | E50: SYS-HRIS | F50: R07 | G50: Payroll Approval / Release | H50: Admin | I50: 45650 | J50: MGR-06 | K50: CHG-42177 | L50: Active
A51: AG-0050 | B51: E016 | C51: Tariq Petrov | D51: HR | E51: SYS-HRIS | F51: R08 | G51: Employee Master Read-Only | H51: Read | I51: 46024 | J51: MGR-04 | K51: CHG-70910 | L51: Active
A52: AG-0051 | B52: E016 | C52: Tariq Petrov | D52: HR | E52: SYS-AD | F52: R09 | G52: Standard Network User | H52: Read | I52: 45789 | J52: MGR-01 | K52: CHG-74789 | L52: Active
A53: AG-0052 | B53: E016 | C53: Tariq Petrov | D53: HR | E53: SYS-HRIS | F53: R06 | G53: Payroll Data Entry | H53: Write | I53: 45535 | J53: MGR-06 | K53: CHG-43862 | L53: Active
A54: AG-0053 | B54: E017 | C54: Isabel Okafor | D54: Finance | E54: SYS-HRIS | F54: R08 | G54: Employee Master Read-Only | H54: Read | I54: 45135 | J54: MGR-08 | K54: CHG-82768 | L54: Revoked | M54: 45826
A55: AG-0054 | B55: E017 | C55: Isabel Okafor | D55: Finance | E55: SYS-ERP | F55: R03 | G55: Vendor Master Maintenance | H55: Write | I55: 45291 | J55: MGR-08 | K55: CHG-68743 | L55: Active
A56: AG-0055 | B56: E017 | C56: Isabel Okafor | D56: Finance | E56: SYS-ERP | F56: R01 | G56: AP Invoice Entry | H56: Write | I56: 45040 | J56: MGR-07 | K56: CHG-41890 | L56: Revoked | M56: 45824
A57: AG-0056 | B57: E017 | C57: Isabel Okafor | D57: Finance | E57: SYS-ERP | F57: R05 | G57: GL Journal Approval | H57: Admin | I57: 45210 | J57: MGR-09 | K57: CHG-55056 | L57: Revoked | M57: 45824
A58: AG-0057 | B58: E017 | C58: Isabel Okafor | D58: Finance | E58: SYS-BANK | F58: R13 | G58: Wire Initiation | H58: Write | I58: 45107 | J58: MGR-08 | K58: CHG-45509 | L58: Active
A59: AG-0058 | B59: E017 | C59: Isabel Okafor | D59: Finance | E59: SYS-BANK | F59: R14 | G59: Wire Approval / Release | H59: Admin | I59: 45296 | J59: MGR-04 | L59: Revoked | M59: 45823
A60: AG-0059 | B60: E018 | C60: Carlos Santos | D60: HR | E60: SYS-AD | F60: R09 | G60: Standard Network User | H60: Read | I60: 46124 | J60: MGR-10 | K60: CHG-78765 | L60: Active
A61: AG-0060 | B61: E018 | C61: Carlos Santos | D61: HR | E61: SYS-HRIS | F61: R07 | G61: Payroll Approval / Release | H61: Admin | I61: 46235 | J61: MGR-04 | K61: CHG-48829 | L61: Active
A62: AG-0061 | B62: E019 | C62: Sophia Abara | D62: Procurement | E62: SYS-AD | F62: R09 | G62: Standard Network User | H62: Read | I62: 45525 | J62: MGR-03 | K62: CHG-93606 | L62: Active
A63: AG-0062 | B63: E019 | C63: Sophia Abara | D63: Procurement | E63: SYS-ERP | F63: R03 | G63: Vendor Master Maintenance | H63: Write | I63: 44952 | J63: MGR-10 | K63: CHG-47268 | L63: Active
A64: AG-0063 | B64: E019 | C64: Sophia Abara | D64: Procurement | E64: SYS-ERP | F64: R01 | G64: AP Invoice Entry | H64: Write | I64: 45304 | J64: MGR-01 | K64: CHG-43092 | L64: Active
A65: AG-0064 | B65: E019 | C65: Sophia Abara | D65: Procurement | E65: SYS-ERP | F65: R02 | G65: AP Payment Approval | H65: Write | I65: 45060 | J65: MGR-07 | L65: Revoked | M65: 45365
A66: AG-0065 | B66: E020 | C66: Diego Ivanov | D66: Payroll | E66: SYS-HRIS | F66: R07 | G66: Payroll Approval / Release | H66: Admin | I66: 45750 | J66: MGR-10 | K66: CHG-88135 | L66: Active
A67: AG-0066 | B67: E020 | C67: Diego Ivanov | D67: Payroll | E67: SYS-HRIS | F67: R06 | G67: Payroll Data Entry | H67: Write | I67: 45859 | J67: MGR-07 | K67: CHG-69049 | L67: Active
A68: AG-0067 | B68: E020 | C68: Diego Ivanov | D68: Payroll | E68: SYS-HRIS | F68: R08 | G68: Employee Master Read-Only | H68: Read | I68: 45926 | J68: MGR-07 | K68: CHG-50026 | L68: Active
A69: AG-0068 | B69: E020 | C69: Diego Ivanov | D69: Payroll | E69: SYS-AD | F69: R09 | G69: Standard Network User | H69: Read | I69: 46081 | J69: MGR-02 | K69: CHG-37235 | L69: Active
A70: AG-0069 | B70: E021 | C70: Kofi Braga | D70: Accounts Payable | E70: SYS-AD | F70: R09 | G70: Standard Network User | H70: Read | I70: 45247 | J70: MGR-01 | K70: CHG-63545 | L70: Active
A71: AG-0070 | B71: E021 | C71: Kofi Braga | D71: Accounts Payable | E71: SYS-ERP | F71: R02 | G71: AP Payment Approval | H71: Write | I71: 45523 | J71: MGR-01 | K71: CHG-40340 | L71: Active
A72: AG-0071 | B72: E021 | C72: Kofi Braga | D72: Accounts Payable | E72: SYS-ERP | F72: R01 | G72: AP Invoice Entry | H72: Write | I72: 45856 | J72: MGR-02 | K72: CHG-40595 | L72: Active
A73: AG-0072 | B73: E022 | C73: Rahul Silva | D73: Treasury | E73: SYS-BANK | F73: R14 | G73: Wire Approval / Release | H73: Admin | I73: 45199 | J73: MGR-03 | L73: Active
A74: AG-0073 | B74: E022 | C74: Rahul Silva | D74: Treasury | E74: SYS-HRIS | F74: R08 | G74: Employee Master Read-Only | H74: Read | I74: 45509 | J74: MGR-05 | K74: CHG-67560 | L74: Active
A75: AG-0074 | B75: E022 | C75: Rahul Silva | D75: Treasury | E75: SYS-AD | F75: R09 | G75: Standard Network User | H75: Read | I75: 45339 | J75: MGR-05 | K75: CHG-75597 | L75: Active
A76: AG-0075 | B76: E022 | C76: Rahul Silva | D76: Treasury | E76: SYS-BANK | F76: R13 | G76: Wire Initiation | H76: Write | I76: 45539 | J76: MGR-01 | K76: CHG-66626 | L76: Active
A77: AG-0076 | B77: E023 | C77: Youssef Andersson | D77: Customer Service | E77: SYS-AD | F77: R09 | G77: Standard Network User | H77: Read | I77: 45034 | J77: MGR-10 | K77: CHG-86955 | L77: Revoked | M77: 46034
A78: AG-0077 | B78: E023 | C78: Youssef Andersson | D78: Customer Service | E78: SYS-HRIS | F78: R08 | G78: Employee Master Read-Only | H78: Read | I78: 45032 | J78: MGR-05 | L78: Revoked | M78: 46034
A79: AG-0078 | B79: E024 | C79: Priya Rossi | D79: Accounts Payable | E79: SYS-HRIS | F79: R08 | G79: Employee Master Read-Only | H79: Read | I79: 45178 | J79: MGR-02 | K79: CHG-71605 | L79: Active
A80: AG-0079 | B80: E024 | C80: Priya Rossi | D80: Accounts Payable | E80: SYS-AD | F80: R09 | G80: Standard Network User | H80: Read | I80: 45270 | J80: MGR-02 | K80: CHG-31079 | L80: Active
A81: AG-0080 | B81: E024 | C81: Priya Rossi | D81: Accounts Payable | E81: SYS-ERP | F81: R02 | G81: AP Payment Approval | H81: Write | I81: 45074 | J81: System Auto-Provision | K81: CHG-62488 | L81: Active
A82: AG-0081 | B82: E025 | C82: Kenji Silva | D82: Customer Service | E82: SYS-AD | F82: R09 | G82: Standard Network User | H82: Read | I82: 46130 | J82: MGR-09 | K82: CHG-10150 | L82: Revoked | M82: 46260
A83: AG-0082 | B83: E025 | C83: Kenji Silva | D83: Customer Service | E83: SYS-CRM | F83: R11 | G83: Sales Order Entry | H83: Write | I83: 45772 | J83: MGR-04 | K83: CHG-77952 | L83: Revoked | M83: 46262
A84: AG-0083 | B84: E025 | C84: Kenji Silva | D84: Customer Service | E84: SYS-HRIS | F84: R08 | G84: Employee Master Read-Only | H84: Read | I84: 46169 | J84: MGR-01 | K84: CHG-36680 | L84: Active
A85: AG-0084 | B85: E026 | C85: Grace Braga | D85: Procurement | E85: SYS-ERP | F85: R03 | G85: Vendor Master Maintenance | H85: Write | I85: 45550 | J85: MGR-04 | K85: CHG-30758 | L85: Revoked | M85: 45967
A86: AG-0085 | B86: E026 | C86: Grace Braga | D86: Procurement | E86: SYS-HRIS | F86: R08 | G86: Employee Master Read-Only | H86: Read | I86: 45022 | J86: MGR-04 | K86: CHG-24871 | L86: Active
A87: AG-0086 | B87: E026 | C87: Grace Braga | D87: Procurement | E87: SYS-AD | F87: R09 | G87: Standard Network User | H87: Read | I87: 45779 | J87: MGR-03 | K87: CHG-75323 | L87: Active
A88: AG-0087 | B88: E026 | C88: Grace Braga | D88: Procurement | E88: SYS-BANK | F88: R13 | G88: Wire Initiation | H88: Write | I88: 45649 | J88: MGR-05 | K88: CHG-64459 | L88: Active
A89: AG-0088 | B89: E026 | C89: Grace Braga | D89: Procurement | E89: SYS-BANK | F89: R14 | G89: Wire Approval / Release | H89: Admin | I89: 45176 | J89: MGR-08 | K89: CHG-82255 | L89: Active
A90: AG-0089 | B90: E027 | C90: Laura Khan | D90: Procurement | E90: SYS-AD | F90: R09 | G90: Standard Network User | H90: Read | I90: 46121 | J90: MGR-09 | K90: CHG-45018 | L90: Active
A91: AG-0090 | B91: E027 | C91: Laura Khan | D91: Procurement | E91: SYS-ERP | F91: R01 | G91: AP Invoice Entry | H91: Write | I91: 45620 | J91: MGR-10 | K91: CHG-86011 | L91: Revoked | M91: 45890
A92: AG-0091 | B92: E027 | C92: Laura Khan | D92: Procurement | E92: SYS-ERP | F92: R03 | G92: Vendor Master Maintenance | H92: Write | I92: 45772 | J92: MGR-09 | K92: CHG-73483 | L92: Revoked | M92: 45892
A93: AG-0092 | B93: E027 | C93: Laura Khan | D93: Procurement | E93: SYS-HRIS | F93: R08 | G93: Employee Master Read-Only | H93: Read | I93: 45701 | J93: MGR-08 | K93: CHG-52176 | L93: Revoked | M93: 45890
A94: AG-0093 | B94: E028 | C94: Maria Haruki | D94: Procurement | E94: SYS-ERP | F94: R03 | G94: Vendor Master Maintenance | H94: Write | I94: 45411 | J94: MGR-07 | K94: CHG-60604 | L94: Active
A95: AG-0094 | B95: E028 | C95: Maria Haruki | D95: Procurement | E95: SYS-ERP | F95: R01 | G95: AP Invoice Entry | H95: Write | I95: 45594 | J95: MGR-03 | K95: CHG-74923 | L95: Active
A96: AG-0095 | B96: E028 | C96: Maria Haruki | D96: Procurement | E96: SYS-AD | F96: R09 | G96: Standard Network User | H96: Read | I96: 45531 | J96: MGR-06 | K96: CHG-23154 | L96: Active
A97: AG-0096 | B97: E028 | C97: Maria Haruki | D97: Procurement | E97: SYS-HRIS | F97: R08 | G97: Employee Master Read-Only | H97: Read | I97: 45465 | J97: MGR-08 | K97: CHG-12011 | L97: Active
A98: AG-0097 | B98: E029 | C98: Carlos Osei | D98: Finance | E98: SYS-ERP | F98: R05 | G98: GL Journal Approval | H98: Admin | I98: 45741 | J98: System Auto-Provision | K98: CHG-20527 | L98: Revoked | M98: 45905
A99: AG-0098 | B99: E029 | C99: Carlos Osei | D99: Finance | E99: SYS-ERP | F99: R01 | G99: AP Invoice Entry | H99: Write | I99: 45705 | J99: MGR-06 | K99: CHG-92155 | L99: Revoked | M99: 45905
A100: AG-0099 | B100: E029 | C100: Carlos Osei | D100: Finance | E100: SYS-AD | F100: R09 | G100: Standard Network User | H100: Read | I100: 45000 | J100: MGR-10 | K100: CHG-18968 | L100: Revoked | M100: 45904
...

Sheet Recertifications
A1: RecertID | B1: EmployeeID | C1: EmployeeName | D1: SystemID | E1: RoleID | F1: RoleName | G1: AccessLevel | H1: ReviewCycleDays | I1: DueDate | J1: Reviewer | K1: CompletedDate | L1: Result | M1: Recert_Status
A2: RC-0001 | B2: E001 | C2: Sophia Chen | D2: SYS-AD | E2: R09 | F2: Standard Network User | G2: Read | H2: 365 | I2: 46260 | J2: MGR-02 | K2: 46243 | L2: Access Confirmed Appropriate | M2: =IF(ISBLANK(K2),IF(TODAY()>I2,"OVERDUE - NOT COMPLETED","PENDING - NOT YET DUE"),IF(K2>I2,"COMPLETED LATE","COMPLETED ON TIME")) -> COMPLETED ON TIME
A3: RC-0002 | B3: E001 | C3: Sophia Chen | D3: SYS-HRIS | E3: R08 | F3: Employee Master Read-Only | G3: Read | H3: 365 | I3: 46071 | J3: MGR-06 | M3: =IF(ISBLANK(K3),IF(TODAY()>I3,"OVERDUE - NOT COMPLETED","PENDING - NOT YET DUE"),IF(K3>I3,"COMPLETED LATE","COMPLETED ON TIME")) -> OVERDUE - NOT COMPLETED
A4: RC-0003 | B4: E001 | C4: Sophia Chen | D4: SYS-AD | E4: R10 | F4: Domain Administrator | G4: Admin | H4: 90 | I4: 46272 | J4: MGR-07 | M4: =IF(ISBLANK(K4),IF(TODAY()>I4,"OVERDUE - NOT COMPLETED","PENDING - NOT YET DUE"),IF(K4>I4,"COMPLETED LATE","COMPLETED ON TIME")) -> OVERDUE - NOT COMPLETED
A5: RC-0004 | B5: E002 | C5: Peter Okafor | D5: SYS-HRIS | E5: R07 | F5: Payroll Approval / Release | G5: Admin | H5: 90 | I5: 46272 | J5: MGR-09 | K5: 46262 | L5: Access Confirmed Appropriate | M5: =IF(ISBLANK(K5),IF(TODAY()>I5,"OVERDUE - NOT COMPLETED","PENDING - NOT YET DUE"),IF(K5>I5,"COMPLETED LATE","COMPLETED ON TIME")) -> COMPLETED ON TIME
A6: RC-0005 | B6: E002 | C6: Peter Okafor | D6: SYS-HRIS | E6: R08 | F6: Employee Master Read-Only | G6: Read | H6: 365 | I6: 46457 | J6: MGR-02 | K6: 46444 | L6: Access Revoked - No Longer Needed | M6: =IF(ISBLANK(K6),IF(TODAY()>I6,"OVERDUE - NOT COMPLETED","PENDING - NOT YET DUE"),IF(K6>I6,"COMPLETED LATE","COMPLETED ON TIME")) -> COMPLETED ON TIME
A7: RC-0006 | B7: E003 | C7: Youssef Chen | D7: SYS-AD | E7: R09 | F7: Standard Network User | G7: Read | H7: 365 | I7: 46234 | J7: MGR-03 | K7: 46224 | L7: Access Confirmed Appropriate | M7: =IF(ISBLANK(K7),IF(TODAY()>I7,"OVERDUE - NOT COMPLETED","PENDING - NOT YET DUE"),IF(K7>I7,"COMPLETED LATE","COMPLETED ON TIME")) -> COMPLETED ON TIME
A8: RC-0007 | B8: E003 | C8: Youssef Chen | D8: SYS-ERP | E8: R03 | F8: Vendor Master Maintenance | G8: Write | H8: 365 | I8: 46076 | J8: MGR-02 | K8: 46083 | L8: Access Revoked - No Longer Needed | M8: =IF(ISBLANK(K8),IF(TODAY()>I8,"OVERDUE - NOT COMPLETED","PENDING - NOT YET DUE"),IF(K8>I8,"COMPLETED LATE","COMPLETED ON TIME")) -> COMPLETED LATE
A9: RC-0008 | B9: E003 | C9: Youssef Chen | D9: SYS-ERP | E9: R01 | F9: AP Invoice Entry | G9: Write | H9: 365 | I9: 45956 | J9: MGR-06 | K9: 45937 | L9: Access Confirmed Appropriate | M9: =IF(ISBLANK(K9),IF(TODAY()>I9,"OVERDUE - NOT COMPLETED","PENDING - NOT YET DUE"),IF(K9>I9,"COMPLETED LATE","COMPLETED ON TIME")) -> COMPLETED ON TIME
A10: RC-0009 | B10: E004 | C10: Omar Khan | D10: SYS-HRIS | E10: R08 | F10: Employee Master Read-Only | G10: Read | H10: 365 | I10: 46084 | J10: MGR-03 | K10: 46065 | L10: Access Confirmed Appropriate | M10: =IF(ISBLANK(K10),IF(TODAY()>I10,"OVERDUE - NOT COMPLETED","PENDING - NOT YET DUE"),IF(K10>I10,"COMPLETED LATE","COMPLETED ON TIME")) -> COMPLETED ON TIME
A11: RC-0010 | B11: E004 | C11: Omar Khan | D11: SYS-AD | E11: R09 | F11: Standard Network User | G11: Read | H11: 365 | I11: 46338 | J11: MGR-06 | K11: 46331 | L11: Access Confirmed Appropriate | M11: =IF(ISBLANK(K11),IF(TODAY()>I11,"OVERDUE - NOT COMPLETED","PENDING - NOT YET DUE"),IF(K11>I11,"COMPLETED LATE","COMPLETED ON TIME")) -> COMPLETED ON TIME
A12: RC-0011 | B12: E005 | C12: Olivia Andersson | D12: SYS-AD | E12: R10 | F12: Domain Administrator | G12: Admin | H12: 90 | I12: 46252 | J12: MGR-09 | K12: 46283 | L12: Access Confirmed Appropriate | M12: =IF(ISBLANK(K12),IF(TODAY()>I12,"OVERDUE - NOT COMPLETED","PENDING - NOT YET DUE"),IF(K12>I12,"COMPLETED LATE","COMPLETED ON TIME")) -> COMPLETED LATE
A13: RC-0012 | B13: E005 | C13: Olivia Andersson | D13: SYS-HRIS | E13: R08 | F13: Employee Master Read-Only | G13: Read | H13: 365 | I13: 46369 | J13: MGR-08 | K13: 46357 | L13: Access Revoked - No Longer Needed | M13: =IF(ISBLANK(K13),IF(TODAY()>I13,"OVERDUE - NOT COMPLETED","PENDING - NOT YET DUE"),IF(K13>I13,"COMPLETED LATE","COMPLETED ON TIME")) -> COMPLETED ON TIME
A14: RC-0013 | B14: E005 | C14: Olivia Andersson | D14: SYS-AD | E14: R09 | F14: Standard Network User | G14: Read | H14: 365 | I14: 46122 | J14: MGR-10 | M14: =IF(ISBLANK(K14),IF(TODAY()>I14,"OVERDUE - NOT COMPLETED","PENDING - NOT YET DUE"),IF(K14>I14,"COMPLETED LATE","COMPLETED ON TIME")) -> OVERDUE - NOT COMPLETED
A15: RC-0014 | B15: E006 | C15: Fatima Santos | D15: SYS-ERP | E15: R03 | F15: Vendor Master Maintenance | G15: Write | H15: 365 | I15: 46410 | J15: MGR-06 | K15: 46407 | L15: Access Revoked - No Longer Needed | M15: =IF(ISBLANK(K15),IF(TODAY()>I15,"OVERDUE - NOT COMPLETED","PENDING - NOT YET DUE"),IF(K15>I15,"COMPLETED LATE","COMPLETED ON TIME")) -> COMPLETED ON TIME
A16: RC-0015 | B16: E006 | C16: Fatima Santos | D16: SYS-AD | E16: R09 | F16: Standard Network User | G16: Read | H16: 365 | I16: 46197 | J16: MGR-08 | K16: 46193 | L16: Access Confirmed Appropriate | M16: =IF(ISBLANK(K16),IF(TODAY()>I16,"OVERDUE - NOT COMPLETED","PENDING - NOT YET DUE"),IF(K16>I16,"COMPLETED LATE","COMPLETED ON TIME")) -> COMPLETED ON TIME
A17: RC-0016 | B17: E007 | C17: Wei Petrov | D17: SYS-AD | E17: R09 | F17: Standard Network User | G17: Read | H17: 365 | I17: 46379 | J17: MGR-06 | K17: 46366 | L17: Access Confirmed Appropriate | M17: =IF(ISBLANK(K17),IF(TODAY()>I17,"OVERDUE - NOT COMPLETED","PENDING - NOT YET DUE"),IF(K17>I17,"COMPLETED LATE","COMPLETED ON TIME")) -> COMPLETED ON TIME
A18: RC-0017 | B18: E008 | C18: Diego Ferreira | D18: SYS-BANK | E18: R14 | F18: Wire Approval / Release | G18: Admin | H18: 90 | I18: 46253 | J18: MGR-07 | K18: 46242 | L18: Access Confirmed Appropriate | M18: =IF(ISBLANK(K18),IF(TODAY()>I18,"OVERDUE - NOT COMPLETED","PENDING - NOT YET DUE"),IF(K18>I18,"COMPLETED LATE","COMPLETED ON TIME")) -> COMPLETED ON TIME
A19: RC-0018 | B19: E008 | C19: Diego Ferreira | D19: SYS-AD | E19: R09 | F19: Standard Network User | G19: Read | H19: 365 | I19: 46261 | J19: MGR-03 | M19: =IF(ISBLANK(K19),IF(TODAY()>I19,"OVERDUE - NOT COMPLETED","PENDING - NOT YET DUE"),IF(K19>I19,"COMPLETED LATE","COMPLETED ON TIME")) -> OVERDUE - NOT COMPLETED
A20: RC-0019 | B20: E008 | C20: Diego Ferreira | D20: SYS-HRIS | E20: R06 | F20: Payroll Data Entry | G20: Write | H20: 365 | I20: 46060 | J20: MGR-08 | K20: 46060 | L20: Access Confirmed Appropriate | M20: =IF(ISBLANK(K20),IF(TODAY()>I20,"OVERDUE - NOT COMPLETED","PENDING - NOT YET DUE"),IF(K20>I20,"COMPLETED LATE","COMPLETED ON TIME")) -> COMPLETED ON TIME
A21: RC-0020 | B21: E008 | C21: Diego Ferreira | D21: SYS-HRIS | E21: R07 | F21: Payroll Approval / Release | G21: Admin | H21: 90 | I21: 46231 | J21: MGR-09 | K21: 46212 | L21: Access Revoked - No Longer Needed | M21: =IF(ISBLANK(K21),IF(TODAY()>I21,"OVERDUE - NOT COMPLETED","PENDING - NOT YET DUE"),IF(K21>I21,"COMPLETED LATE","COMPLETED ON TIME")) -> COMPLETED ON TIME
A22: RC-0021 | B22: E009 | C22: Omar Diallo | D22: SYS-AD | E22: R10 | F22: Domain Administrator | G22: Admin | H22: 90 | I22: 46253 | J22: MGR-05 | M22: =IF(ISBLANK(K22),IF(TODAY()>I22,"OVERDUE - NOT COMPLETED","PENDING - NOT YET DUE"),IF(K22>I22,"COMPLETED LATE","COMPLETED ON TIME")) -> OVERDUE - NOT COMPLETED
A23: RC-0022 | B23: E009 | C23: Omar Diallo | D23: SYS-HRIS | E23: R08 | F23: Employee Master Read-Only | G23: Read | H23: 365 | I23: 46386 | J23: MGR-02 | M23: =IF(ISBLANK(K23),IF(TODAY()>I23,"OVERDUE - NOT COMPLETED","PENDING - NOT YET DUE"),IF(K23>I23,"COMPLETED LATE","COMPLETED ON TIME")) -> PENDING - NOT YET DUE
A24: RC-0023 | B24: E010 | C24: Ingrid Khan | D24: SYS-AD | E24: R09 | F24: Standard Network User | G24: Read | H24: 365 | I24: 46445 | J24: MGR-10 | M24: =IF(ISBLANK(K24),IF(TODAY()>I24,"OVERDUE - NOT COMPLETED","PENDING - NOT YET DUE"),IF(K24>I24,"COMPLETED LATE","COMPLETED ON TIME")) -> PENDING - NOT YET DUE
A25: RC-0024 | B25: E010 | C25: Ingrid Khan | D25: SYS-BANK | E25: R13 | F25: Wire Initiation | G25: Write | H25: 365 | I25: 46279 | J25: MGR-04 | K25: 46274 | L25: Access Confirmed Appropriate | M25: =IF(ISBLANK(K25),IF(TODAY()>I25,"OVERDUE - NOT COMPLETED","PENDING - NOT YET DUE"),IF(K25>I25,"COMPLETED LATE","COMPLETED ON TIME")) -> COMPLETED ON TIME
A26: RC-0025 | B26: E010 | C26: Ingrid Khan | D26: SYS-BANK | E26: R14 | F26: Wire Approval / Release | G26: Admin | H26: 90 | I26: 46210 | J26: MGR-09 | K26: 46194 | L26: Access Revoked - No Longer Needed | M26: =IF(ISBLANK(K26),IF(TODAY()>I26,"OVERDUE - NOT COMPLETED","PENDING - NOT YET DUE"),IF(K26>I26,"COMPLETED LATE","COMPLETED ON TIME")) -> COMPLETED ON TIME
A27: RC-0026 | B27: E011 | C27: Ingrid Reyes | D27: SYS-ERP | E27: R01 | F27: AP Invoice Entry | G27: Write | H27: 365 | I27: 45962 | J27: MGR-07 | K27: 45954 | L27: Access Confirmed Appropriate | M27: =IF(ISBLANK(K27),IF(TODAY()>I27,"OVERDUE - NOT COMPLETED","PENDING - NOT YET DUE"),IF(K27>I27,"COMPLETED LATE","COMPLETED ON TIME")) -> COMPLETED ON TIME
A28: RC-0027 | B28: E011 | C28: Ingrid Reyes | D28: SYS-ERP | E28: R03 | F28: Vendor Master Maintenance | G28: Write | H28: 365 | I28: 46271 | J28: MGR-04 | K28: 46251 | L28: Access Confirmed Appropriate | M28: =IF(ISBLANK(K28),IF(TODAY()>I28,"OVERDUE - NOT COMPLETED","PENDING - NOT YET DUE"),IF(K28>I28,"COMPLETED LATE","COMPLETED ON TIME")) -> COMPLETED ON TIME
A29: RC-0028 | B29: E011 | C29: Ingrid Reyes | D29: SYS-AD | E29: R09 | F29: Standard Network User | G29: Read | H29: 365 | I29: 46054 | J29: MGR-01 | K29: 46044 | L29: Access Confirmed Appropriate | M29: =IF(ISBLANK(K29),IF(TODAY()>I29,"OVERDUE - NOT COMPLETED","PENDING - NOT YET DUE"),IF(K29>I29,"COMPLETED LATE","COMPLETED ON TIME")) -> COMPLETED ON TIME
A30: RC-0029 | B30: E011 | C30: Ingrid Reyes | D30: SYS-ERP | E30: R02 | F30: AP Payment Approval | G30: Write | H30: 365 | I30: 46393 | J30: MGR-08 | K30: 46389 | L30: Access Confirmed Appropriate | M30: =IF(ISBLANK(K30),IF(TODAY()>I30,"OVERDUE - NOT COMPLETED","PENDING - NOT YET DUE"),IF(K30>I30,"COMPLETED LATE","COMPLETED ON TIME")) -> COMPLETED ON TIME
A31: RC-0030 | B31: E012 | C31: Zara Santos | D31: SYS-AD | E31: R09 | F31: Standard Network User | G31: Read | H31: 365 | I31: 45955 | J31: MGR-05 | K31: 45968 | L31: Access Confirmed Appropriate | M31: =IF(ISBLANK(K31),IF(TODAY()>I31,"OVERDUE - NOT COMPLETED","PENDING - NOT YET DUE"),IF(K31>I31,"COMPLETED LATE","COMPLETED ON TIME")) -> COMPLETED LATE
A32: RC-0031 | B32: E012 | C32: Zara Santos | D32: SYS-AD | E32: R10 | F32: Domain Administrator | G32: Admin | H32: 90 | I32: 46324 | J32: MGR-07 | K32: 46307 | L32: Access Confirmed Appropriate | M32: =IF(ISBLANK(K32),IF(TODAY()>I32,"OVERDUE - NOT COMPLETED","PENDING - NOT YET DUE"),IF(K32>I32,"COMPLETED LATE","COMPLETED ON TIME")) -> COMPLETED ON TIME
A33: RC-0032 | B33: E012 | C33: Zara Santos | D33: SYS-HRIS | E33: R08 | F33: Employee Master Read-Only | G33: Read | H33: 365 | I33: 46113 | J33: MGR-05 | K33: 46206 | L33: Access Confirmed Appropriate | M33: =IF(ISBLANK(K33),IF(TODAY()>I33,"OVERDUE - NOT COMPLETED","PENDING - NOT YET DUE"),IF(K33>I33,"COMPLETED LATE","COMPLETED ON TIME")) -> COMPLETED LATE
A34: RC-0033 | B34: E013 | C34: Omar Ferreira | D34: SYS-ERP | E34: R05 | F34: GL Journal Approval | G34: Admin | H34: 90 | I34: 46304 | J34: MGR-07 | K34: 46292 | L34: Access Confirmed Appropriate | M34: =IF(ISBLANK(K34),IF(TODAY()>I34,"OVERDUE - NOT COMPLETED","PENDING - NOT YET DUE"),IF(K34>I34,"COMPLETED LATE","COMPLETED ON TIME")) -> COMPLETED ON TIME
A35: RC-0034 | B35: E014 | C35: Raj Osei | D35: SYS-BANK | E35: R13 | F35: Wire Initiation | G35: Write | H35: 365 | I35: 46294 | J35: MGR-09 | M35: =IF(ISBLANK(K35),IF(TODAY()>I35,"OVERDUE - NOT COMPLETED","PENDING - NOT YET DUE"),IF(K35>I35,"COMPLETED LATE","COMPLETED ON TIME")) -> PENDING - NOT YET DUE
A36: RC-0035 | B36: E015 | C36: Zara Silva | D36: SYS-HRIS | E36: R08 | F36: Employee Master Read-Only | G36: Read | H36: 365 | I36: 46358 | J36: MGR-10 | K36: 46353 | L36: Access Revoked - No Longer Needed | M36: =IF(ISBLANK(K36),IF(TODAY()>I36,"OVERDUE - NOT COMPLETED","PENDING - NOT YET DUE"),IF(K36>I36,"COMPLETED LATE","COMPLETED ON TIME")) -> COMPLETED ON TIME
A37: RC-0036 | B37: E015 | C37: Zara Silva | D37: SYS-AD | E37: R09 | F37: Standard Network User | G37: Read | H37: 365 | I37: 45999 | J37: MGR-06 | K37: 45990 | L37: Access Confirmed Appropriate | M37: =IF(ISBLANK(K37),IF(TODAY()>I37,"OVERDUE - NOT COMPLETED","PENDING - NOT YET DUE"),IF(K37>I37,"COMPLETED LATE","COMPLETED ON TIME")) -> COMPLETED ON TIME
A38: RC-0037 | B38: E015 | C38: Zara Silva | D38: SYS-BANK | E38: R13 | F38: Wire Initiation | G38: Write | H38: 365 | I38: 46088 | J38: MGR-08 | K38: 46087 | L38: Access Confirmed Appropriate | M38: =IF(ISBLANK(K38),IF(TODAY()>I38,"OVERDUE - NOT COMPLETED","PENDING - NOT YET DUE"),IF(K38>I38,"COMPLETED LATE","COMPLETED ON TIME")) -> COMPLETED ON TIME
A39: RC-0038 | B39: E015 | C39: Zara Silva | D39: SYS-BANK | E39: R14 | F39: Wire Approval / Release | G39: Admin | H39: 90 | I39: 46263 | J39: MGR-01 | M39: =IF(ISBLANK(K39),IF(TODAY()>I39,"OVERDUE - NOT COMPLETED","PENDING - NOT YET DUE"),IF(K39>I39,"COMPLETED LATE","COMPLETED ON TIME")) -> OVERDUE - NOT COMPLETED
A40: RC-0039 | B40: E016 | C40: Tariq Petrov | D40: SYS-HRIS | E40: R07 | F40: Payroll Approval / Release | G40: Admin | H40: 90 | I40: 46324 | J40: MGR-03 | K40: 46320 | L40: Escalated for Review | M40: =IF(ISBLANK(K40),IF(TODAY()>I40,"OVERDUE - NOT COMPLETED","PENDING - NOT YET DUE"),IF(K40>I40,"COMPLETED LATE","COMPLETED ON TIME")) -> COMPLETED ON TIME
A41: RC-0040 | B41: E016 | C41: Tariq Petrov | D41: SYS-HRIS | E41: R08 | F41: Employee Master Read-Only | G41: Read | H41: 365 | I41: 45953 | J41: MGR-03 | M41: =IF(ISBLANK(K41),IF(TODAY()>I41,"OVERDUE - NOT COMPLETED","PENDING - NOT YET DUE"),IF(K41>I41,"COMPLETED LATE","COMPLETED ON TIME")) -> OVERDUE - NOT COMPLETED
A42: RC-0041 | B42: E016 | C42: Tariq Petrov | D42: SYS-AD | E42: R09 | F42: Standard Network User | G42: Read | H42: 365 | I42: 46288 | J42: MGR-07 | K42: 46287 | L42: Escalated for Review | M42: =IF(ISBLANK(K42),IF(TODAY()>I42,"OVERDUE - NOT COMPLETED","PENDING - NOT YET DUE"),IF(K42>I42,"COMPLETED LATE","COMPLETED ON TIME")) -> COMPLETED ON TIME
A43: RC-0042 | B43: E016 | C43: Tariq Petrov | D43: SYS-HRIS | E43: R06 | F43: Payroll Data Entry | G43: Write | H43: 365 | I43: 46297 | J43: MGR-06 | K43: 46295 | L43: Escalated for Review | M43: =IF(ISBLANK(K43),IF(TODAY()>I43,"OVERDUE - NOT COMPLETED","PENDING - NOT YET DUE"),IF(K43>I43,"COMPLETED LATE","COMPLETED ON TIME")) -> COMPLETED ON TIME
A44: RC-0043 | B44: E017 | C44: Isabel Okafor | D44: SYS-ERP | E44: R03 | F44: Vendor Master Maintenance | G44: Write | H44: 365 | I44: 46325 | J44: MGR-06 | K44: 46318 | L44: Access Confirmed Appropriate | M44: =IF(ISBLANK(K44),IF(TODAY()>I44,"OVERDUE - NOT COMPLETED","PENDING - NOT YET DUE"),IF(K44>I44,"COMPLETED LATE","COMPLETED ON TIME")) -> COMPLETED ON TIME
A45: RC-0044 | B45: E017 | C45: Isabel Okafor | D45: SYS-BANK | E45: R13 | F45: Wire Initiation | G45: Write | H45: 365 | I45: 46429 | J45: MGR-09 | K45: 46412 | L45: Access Confirmed Appropriate | M45: =IF(ISBLANK(K45),IF(TODAY()>I45,"OVERDUE - NOT COMPLETED","PENDING - NOT YET DUE"),IF(K45>I45,"COMPLETED LATE","COMPLETED ON TIME")) -> COMPLETED ON TIME
A46: RC-0045 | B46: E018 | C46: Carlos Santos | D46: SYS-AD | E46: R09 | F46: Standard Network User | G46: Read | H46: 365 | I46: 46374 | J46: MGR-04 | K46: 46365 | L46: Access Confirmed Appropriate | M46: =IF(ISBLANK(K46),IF(TODAY()>I46,"OVERDUE - NOT COMPLETED","PENDING - NOT YET DUE"),IF(K46>I46,"COMPLETED LATE","COMPLETED ON TIME")) -> COMPLETED ON TIME
A47: RC-0046 | B47: E018 | C47: Carlos Santos | D47: SYS-HRIS | E47: R07 | F47: Payroll Approval / Release | G47: Admin | H47: 90 | I47: 46211 | J47: MGR-08 | K47: 46240 | L47: Access Confirmed Appropriate | M47: =IF(ISBLANK(K47),IF(TODAY()>I47,"OVERDUE - NOT COMPLETED","PENDING - NOT YET DUE"),IF(K47>I47,"COMPLETED LATE","COMPLETED ON TIME")) -> COMPLETED LATE
A48: RC-0047 | B48: E019 | C48: Sophia Abara | D48: SYS-AD | E48: R09 | F48: Standard Network User | G48: Read | H48: 365 | I48: 46273 | J48: MGR-02 | K48: 46264 | L48: Access Confirmed Appropriate | M48: =IF(ISBLANK(K48),IF(TODAY()>I48,"OVERDUE - NOT COMPLETED","PENDING - NOT YET DUE"),IF(K48>I48,"COMPLETED LATE","COMPLETED ON TIME")) -> COMPLETED ON TIME
A49: RC-0048 | B49: E019 | C49: Sophia Abara | D49: SYS-ERP | E49: R01 | F49: AP Invoice Entry | G49: Write | H49: 365 | I49: 46096 | J49: MGR-06 | K49: 46093 | L49: Access Confirmed Appropriate | M49: =IF(ISBLANK(K49),IF(TODAY()>I49,"OVERDUE - NOT COMPLETED","PENDING - NOT YET DUE"),IF(K49>I49,"COMPLETED LATE","COMPLETED ON TIME")) -> COMPLETED ON TIME
A50: RC-0049 | B50: E020 | C50: Diego Ivanov | D50: SYS-HRIS | E50: R07 | F50: Payroll Approval / Release | G50: Admin | H50: 90 | I50: 46319 | J50: MGR-01 | K50: 46301 | L50: Access Confirmed Appropriate | M50: =IF(ISBLANK(K50),IF(TODAY()>I50,"OVERDUE - NOT COMPLETED","PENDING - NOT YET DUE"),IF(K50>I50,"COMPLETED LATE","COMPLETED ON TIME")) -> COMPLETED ON TIME
A51: RC-0050 | B51: E020 | C51: Diego Ivanov | D51: SYS-HRIS | E51: R06 | F51: Payroll Data Entry | G51: Write | H51: 365 | I51: 46050 | J51: MGR-10 | K51: 46048 | L51: Access Confirmed Appropriate | M51: =IF(ISBLANK(K51),IF(TODAY()>I51,"OVERDUE - NOT COMPLETED","PENDING - NOT YET DUE"),IF(K51>I51,"COMPLETED LATE","COMPLETED ON TIME")) -> COMPLETED ON TIME
A52: RC-0051 | B52: E020 | C52: Diego Ivanov | D52: SYS-HRIS | E52: R08 | F52: Employee Master Read-Only | G52: Read | H52: 365 | I52: 46456 | J52: MGR-07 | K52: 46438 | L52: Access Confirmed Appropriate | M52: =IF(ISBLANK(K52),IF(TODAY()>I52,"OVERDUE - NOT COMPLETED","PENDING - NOT YET DUE"),IF(K52>I52,"COMPLETED LATE","COMPLETED ON TIME")) -> COMPLETED ON TIME
A53: RC-0052 | B53: E020 | C53: Diego Ivanov | D53: SYS-AD | E53: R09 | F53: Standard Network User | G53: Read | H53: 365 | I53: 45993 | J53: MGR-08 | K53: 46093 | L53: Access Confirmed Appropriate | M53: =IF(ISBLANK(K53),IF(TODAY()>I53,"OVERDUE - NOT COMPLETED","PENDING - NOT YET DUE"),IF(K53>I53,"COMPLETED LATE","COMPLETED ON TIME")) -> COMPLETED LATE
... A57: RC-0056 | B57: E022 | C57: Rahul Silva | D57: SYS-AD | E57: R09 | F57: Standard Network User | G57: Read | H57: 365 | I57: 46464 | J57: MGR-02 | K57: 46459 | L57: Escalated for Review | M57: =IF(ISBLANK(K57),IF(TODAY()>I57,"OVERDUE - NOT COMPLETED","PENDING - NOT YET DUE"),IF(K57>I57,"COMPLETED LATE","COMPLETED ON TIME")) -> COMPLETED ON TIME
A58: RC-0057 | B58: E024 | C58: Priya Rossi | D58: SYS-HRIS | E58: R08 | F58: Employee Master Read-Only | G58: Read | H58: 365 | I58: 46263 | J58: MGR-10 | M58: =IF(ISBLANK(K58),IF(TODAY()>I58,"OVERDUE - NOT COMPLETED","PENDING - NOT YET DUE"),IF(K58>I58,"COMPLETED LATE","COMPLETED ON TIME")) -> OVERDUE - NOT COMPLETED
A59: RC-0058 | B59: E024 | C59: Priya Rossi | D59: SYS-ERP | E59: R02 | F59: AP Payment Approval | G59: Write | H59: 365 | I59: 46189 | J59: MGR-04 | K59: 46176 | L59: Escalated for Review | M59: =IF(ISBLANK(K59),IF(TODAY()>I59,"OVERDUE - NOT COMPLETED","PENDING - NOT YET DUE"),IF(K59>I59,"COMPLETED LATE","COMPLETED ON TIME")) -> COMPLETED ON TIME
A60: RC-0059 | B60: E025 | C60: Kenji Silva | D60: SYS-HRIS | E60: R08 | F60: Employee Master Read-Only | G60: Read | H60: 365 | I60: 46214 | J60: MGR-05 | K60: 46202 | L60: Access Confirmed Appropriate | M60: =IF(ISBLANK(K60),IF(TODAY()>I60,"OVERDUE - NOT COMPLETED","PENDING - NOT YET DUE"),IF(K60>I60,"COMPLETED LATE","COMPLETED ON TIME")) -> COMPLETED ON TIME
A61: RC-0060 | B61: E026 | C61: Grace Braga | D61: SYS-HRIS | E61: R08 | F61: Employee Master Read-Only | G61: Read | H61: 365 | I61: 45979 | J61: MGR-03 | K61: 45964 | L61: Access Confirmed Appropriate | M61: =IF(ISBLANK(K61),IF(TODAY()>I61,"OVERDUE - NOT COMPLETED","PENDING - NOT YET DUE"),IF(K61>I61,"COMPLETED LATE","COMPLETED ON TIME")) -> COMPLETED ON TIME
A62: RC-0061 | B62: E026 | C62: Grace Braga | D62: SYS-AD | E62: R09 | F62: Standard Network User | G62: Read | H62: 365 | I62: 46065 | J62: MGR-06 | K62: 46055 | L62: Access Confirmed Appropriate | M62: =IF(ISBLANK(K62),IF(TODAY()>I62,"OVERDUE - NOT COMPLETED","PENDING - NOT YET DUE"),IF(K62>I62,"COMPLETED LATE","COMPLETED ON TIME")) -> COMPLETED ON TIME
A63: RC-0062 | B63: E026 | C63: Grace Braga | D63: SYS-BANK | E63: R14 | F63: Wire Approval / Release | G63: Admin | H63: 90 | I63: 46324 | J63: MGR-09 | M63: =IF(ISBLANK(K63),IF(TODAY()>I63,"OVERDUE - NOT COMPLETED","PENDING - NOT YET DUE"),IF(K63>I63,"COMPLETED LATE","COMPLETED ON TIME")) -> PENDING - NOT YET DUE
A64: RC-0063 | B64: E027 | C64: Laura Khan | D64: SYS-AD | E64: R09 | F64: Standard Network User | G64: Read | H64: 365 | I64: 46191 | J64: MGR-08 | K64: 46198 | L64: Access Confirmed Appropriate | M64: =IF(ISBLANK(K64),IF(TODAY()>I64,"OVERDUE - NOT COMPLETED","PENDING - NOT YET DUE"),IF(K64>I64,"COMPLETED LATE","COMPLETED ON TIME")) -> COMPLETED LATE
A65: RC-0064 | B65: E028 | C65: Maria Haruki | D65: SYS-ERP | E65: R03 | F65: Vendor Master Maintenance | G65: Write | H65: 365 | I65: 46346 | J65: MGR-04 | K65: 46341 | L65: Access Confirmed Appropriate | M65: =IF(ISBLANK(K65),IF(TODAY()>I65,"OVERDUE - NOT COMPLETED","PENDING - NOT YET DUE"),IF(K65>I65,"COMPLETED LATE","COMPLETED ON TIME")) -> COMPLETED ON TIME
A66: RC-0065 | B66: E028 | C66: Maria Haruki | D66: SYS-AD | E66: R09 | F66: Standard Network User | G66: Read | H66: 365 | I66: 46081 | J66: MGR-08 | K66: 46067 | L66: Access Confirmed Appropriate | M66: =IF(ISBLANK(K66),IF(TODAY()>I66,"OVERDUE - NOT COMPLETED","PENDING - NOT YET DUE"),IF(K66>I66,"COMPLETED LATE","COMPLETED ON TIME")) -> COMPLETED ON TIME
A67: RC-0066 | B67: E030 | C67: Isabel Nakamura | D67: SYS-ERP | E67: R03 | F67: Vendor Master Maintenance | G67: Write | H67: 365 | I67: 46320 | J67: MGR-09 | K67: 46313 | L67: Access Confirmed Appropriate | M67: =IF(ISBLANK(K67),IF(TODAY()>I67,"OVERDUE - NOT COMPLETED","PENDING - NOT YET DUE"),IF(K67>I67,"COMPLETED LATE","COMPLETED ON TIME")) -> COMPLETED ON TIME
A68: RC-0067 | B68: E030 | C68: Isabel Nakamura | D68: SYS-ERP | E68: R01 | F68: AP Invoice Entry | G68: Write | H68: 365 | I68: 45969 | J68: MGR-05 | K68: 45949 | L68: Access Confirmed Appropriate | M68: =IF(ISBLANK(K68),IF(TODAY()>I68,"OVERDUE - NOT COMPLETED","PENDING - NOT YET DUE"),IF(K68>I68,"COMPLETED LATE","COMPLETED ON TIME")) -> COMPLETED ON TIME
A69: RC-0068 | B69: E031 | C69: Adam Rossi | D69: SYS-AD | E69: R09 | F69: Standard Network User | G69: Read | H69: 365 | I69: 46028 | J69: MGR-07 | M69: =IF(ISBLANK(K69),IF(TODAY()>I69,"OVERDUE - NOT COMPLETED","PENDING - NOT YET DUE"),IF(K69>I69,"COMPLETED LATE","COMPLETED ON TIME")) -> OVERDUE - NOT COMPLETED
A70: RC-0069 | B70: E031 | C70: Adam Rossi | D70: SYS-HRIS | E70: R08 | F70: Employee Master Read-Only | G70: Read | H70: 365 | I70: 46330 | J70: MGR-06 | M70: =IF(ISBLANK(K70),IF(TODAY()>I70,"OVERDUE - NOT COMPLETED","PENDING - NOT YET DUE"),IF(K70>I70,"COMPLETED LATE","COMPLETED ON TIME")) -> PENDING - NOT YET DUE
A71: RC-0070 | B71: E031 | C71: Adam Rossi | D71: SYS-CRM | E71: R11 | F71: Sales Order Entry | G71: Write | H71: 365 | I71: 46117 | J71: MGR-06 | K71: 46115 | L71: Access Confirmed Appropriate | M71: =IF(ISBLANK(K71),IF(TODAY()>I71,"OVERDUE - NOT COMPLETED","PENDING - NOT YET DUE"),IF(K71>I71,"COMPLETED LATE","COMPLETED ON TIME")) -> COMPLETED ON TIME
A72: RC-0071 | B72: E031 | C72: Adam Rossi | D72: SYS-HRIS | E72: R06 | F72: Payroll Data Entry | G72: Write | H72: 365 | I72: 46204 | J72: MGR-10 | K72: 46201 | L72: Access Confirmed Appropriate | M72: =IF(ISBLANK(K72),IF(TODAY()>I72,"OVERDUE - NOT COMPLETED","PENDING - NOT YET DUE"),IF(K72>I72,"COMPLETED LATE","COMPLETED ON TIME")) -> COMPLETED ON TIME
A73: RC-0072 | B73: E032 | C73: Olivia Kim | D73: SYS-HRIS | E73: R06 | F73: Payroll Data Entry | G73: Write | H73: 365 | I73: 46292 | J73: MGR-03 | M73: =IF(ISBLANK(K73),IF(TODAY()>I73,"OVERDUE - NOT COMPLETED","PENDING - NOT YET DUE"),IF(K73>I73,"COMPLETED LATE","COMPLETED ON TIME")) -> PENDING - NOT YET DUE
A74: RC-0073 | B74: E032 | C74: Olivia Kim | D74: SYS-HRIS | E74: R08 | F74: Employee Master Read-Only | G74: Read | H74: 365 | I74: 45964 | J74: MGR-01 | M74: =IF(ISBLANK(K74),IF(TODAY()>I74,"OVERDUE - NOT COMPLETED","PENDING - NOT YET DUE"),IF(K74>I74,"COMPLETED LATE","COMPLETED ON TIME")) -> OVERDUE - NOT COMPLETED
A75: RC-0074 | B75: E032 | C75: Olivia Kim | D75: SYS-AD | E75: R09 | F75: Standard Network User | G75: Read | H75: 365 | I75: 46449 | J75: MGR-08 | M75: =IF(ISBLANK(K75),IF(TODAY()>I75,"OVERDUE - NOT COMPLETED","PENDING - NOT YET DUE"),IF(K75>I75,"COMPLETED LATE","COMPLETED ON TIME")) -> PENDING - NOT YET DUE
A76: RC-0075 | B76: E033 | C76: Liam Garcia | D76: SYS-HRIS | E76: R06 | F76: Payroll Data Entry | G76: Write | H76: 365 | I76: 46244 | J76: MGR-03 | K76: 46225 | L76: Access Confirmed Appropriate | M76: =IF(ISBLANK(K76),IF(TODAY()>I76,"OVERDUE - NOT COMPLETED","PENDING - NOT YET DUE"),IF(K76>I76,"COMPLETED LATE","COMPLETED ON TIME")) -> COMPLETED ON TIME
A77: RC-0076 | B77: E034 | C77: Rahul Nakamura | D77: SYS-ERP | E77: R03 | F77: Vendor Master Maintenance | G77: Write | H77: 365 | I77: 46439 | J77: MGR-09 | K77: 46421 | L77: Access Confirmed Appropriate | M77: =IF(ISBLANK(K77),IF(TODAY()>I77,"OVERDUE - NOT COMPLETED","PENDING - NOT YET DUE"),IF(K77>I77,"COMPLETED LATE","COMPLETED ON TIME")) -> COMPLETED ON TIME
A78: RC-0077 | B78: E034 | C78: Rahul Nakamura | D78: SYS-AD | E78: R09 | F78: Standard Network User | G78: Read | H78: 365 | I78: 46295 | J78: MGR-06 | K78: 46282 | L78: Escalated for Review | M78: =IF(ISBLANK(K78),IF(TODAY()>I78,"OVERDUE - NOT COMPLETED","PENDING - NOT YET DUE"),IF(K78>I78,"COMPLETED LATE","COMPLETED ON TIME")) -> COMPLETED ON TIME
A79: RC-0078 | B79: E035 | C79: Chloe Kowalski | D79: SYS-ERP | E79: R03 | F79: Vendor Master Maintenance | G79: Write | H79: 365 | I79: 45945 | J79: MGR-10 | K79: 46187 | L79: Escalated for Review | M79: =IF(ISBLANK(K79),IF(TODAY()>I79,"OVERDUE - NOT COMPLETED","PENDING - NOT YET DUE"),IF(K79>I79,"COMPLETED LATE","COMPLETED ON TIME")) -> COMPLETED LATE
A80: RC-0079 | B80: E035 | C80: Chloe Kowalski | D80: SYS-ERP | E80: R01 | F80: AP Invoice Entry | G80: Write | H80: 365 | I80: 46409 | J80: MGR-03 | K80: 46390 | L80: Access Confirmed Appropriate | M80: =IF(ISBLANK(K80),IF(TODAY()>I80,"OVERDUE - NOT COMPLETED","PENDING - NOT YET DUE"),IF(K80>I80,"COMPLETED LATE","COMPLETED ON TIME")) -> COMPLETED ON TIME
A81: RC-0080 | B81: E035 | C81: Chloe Kowalski | D81: SYS-ERP | E81: R02 | F81: AP Payment Approval | G81: Write | H81: 365 | I81: 46166 | J81: MGR-01 | K81: 46163 | L81: Access Confirmed Appropriate | M81: =IF(ISBLANK(K81),IF(TODAY()>I81,"OVERDUE - NOT COMPLETED","PENDING - NOT YET DUE"),IF(K81>I81,"COMPLETED LATE","COMPLETED ON TIME")) -> COMPLETED ON TIME
A82: RC-0081 | B82: E036 | C82: Priya Schmidt | D82: SYS-ERP | E82: R03 | F82: Vendor Master Maintenance | G82: Write | H82: 365 | I82: 46346 | J82: MGR-03 | K82: 46340 | L82: Access Confirmed Appropriate | M82: =IF(ISBLANK(K82),IF(TODAY()>I82,"OVERDUE - NOT COMPLETED","PENDING - NOT YET DUE"),IF(K82>I82,"COMPLETED LATE","COMPLETED ON TIME")) -> COMPLETED ON TIME
A83: RC-0082 | B83: E036 | C83: Priya Schmidt | D83: SYS-HRIS | E83: R08 | F83: Employee Master Read-Only | G83: Read | H83: 365 | I83: 46400 | J83: MGR-01 | K83: 46384 | L83: Access Confirmed Appropriate | M83: =IF(ISBLANK(K83),IF(TODAY()>I83,"OVERDUE - NOT COMPLETED","PENDING - NOT YET DUE"),IF(K83>I83,"COMPLETED LATE","COMPLETED ON TIME")) -> COMPLETED ON TIME
A84: RC-0083 | B84: E036 | C84: Priya Schmidt | D84: SYS-ERP | E84: R01 | F84: AP Invoice Entry | G84: Write | H84: 365 | I84: 46407 | J84: MGR-09 | K84: 46402 | L84: Access Confirmed Appropriate | M84: =IF(ISBLANK(K84),IF(TODAY()>I84,"OVERDUE - NOT COMPLETED","PENDING - NOT YET DUE"),IF(K84>I84,"COMPLETED LATE","COMPLETED ON TIME")) -> COMPLETED ON TIME
A85: RC-0084 | B85: E037 | C85: Sanjay Dubois | D85: SYS-HRIS | E85: R08 | F85: Employee Master Read-Only | G85: Read | H85: 365 | I85: 46188 | J85: MGR-10 | K85: 46181 | L85: Access Confirmed Appropriate | M85: =IF(ISBLANK(K85),IF(TODAY()>I85,"OVERDUE - NOT COMPLETED","PENDING - NOT YET DUE"),IF(K85>I85,"COMPLETED LATE","COMPLETED ON TIME")) -> COMPLETED ON TIME
A86: RC-0085 | B86: E037 | C86: Sanjay Dubois | D86: SYS-AD | E86: R09 | F86: Standard Network User | G86: Read | H86: 365 | I86: 46222 | J86: MGR-05 | K86: 46207 | L86: Access Confirmed Appropriate | M86: =IF(ISBLANK(K86),IF(TODAY()>I86,"OVERDUE - NOT COMPLETED","PENDING - NOT YET DUE"),IF(K86>I86,"COMPLETED LATE","COMPLETED ON TIME")) -> COMPLETED ON TIME
A87: RC-0086 | B87: E038 | C87: Victor Chen | D87: SYS-HRIS | E87: R07 | F87: Payroll Approval / Release | G87: Admin | H87: 90 | I87: 46263 | J87: MGR-05 | M87: =IF(ISBLANK(K87),IF(TODAY()>I87,"OVERDUE - NOT COMPLETED","PENDING - NOT YET DUE"),IF(K87>I87,"COMPLETED LATE","COMPLETED ON TIME")) -> OVERDUE - NOT COMPLETED
A88: RC-0087 | B88: E038 | C88: Victor Chen | D88: SYS-HRIS | E88: R06 | F88: Payroll Data Entry | G88: Write | H88: 365 | I88: 46322 | J88: MGR-06 | K88: 46318 | L88: Access Confirmed Appropriate | M88: =IF(ISBLANK(K88),IF(TODAY()>I88,"OVERDUE - NOT COMPLETED","PENDING - NOT YET DUE"),IF(K88>I88,"COMPLETED LATE","COMPLETED ON TIME")) -> COMPLETED ON TIME
A89: RC-0088 | B89: E038 | C89: Victor Chen | D89: SYS-AD | E89: R09 | F89: Standard Network User | G89: Read | H89: 365 | I89: 45998 | J89: MGR-06 | K89: 45978 | L89: Access Confirmed Appropriate | M89: =IF(ISBLANK(K89),IF(TODAY()>I89,"OVERDUE - NOT COMPLETED","PENDING - NOT YET DUE"),IF(K89>I89,"COMPLETED LATE","COMPLETED ON TIME")) -> COMPLETED ON TIME
A90: RC-0089 | B90: E038 | C90: Victor Chen | D90: SYS-HRIS | E90: R08 | F90: Employee Master Read-Only | G90: Read | H90: 365 | I90: 46124 | J90: MGR-09 | K90: 46160 | L90: Access Confirmed Appropriate | M90: =IF(ISBLANK(K90),IF(TODAY()>I90,"OVERDUE - NOT COMPLETED","PENDING - NOT YET DUE"),IF(K90>I90,"COMPLETED LATE","COMPLETED ON TIME")) -> COMPLETED LATE
A91: RC-0090 | B91: E038 | C91: Victor Chen | D91: SYS-ERP | E91: R01 | F91: AP Invoice Entry | G91: Write | H91: 365 | I91: 46163 | J91: MGR-04 | M91: =IF(ISBLANK(K91),IF(TODAY()>I91,"OVERDUE - NOT COMPLETED","PENDING - NOT YET DUE"),IF(K91>I91,"COMPLETED LATE","COMPLETED ON TIME")) -> OVERDUE - NOT COMPLETED
A92: RC-0091 | B92: E039 | C92: Olivia Reyes | D92: SYS-ERP | E92: R01 | F92: AP Invoice Entry | G92: Write | H92: 365 | I92: 45971 | J92: MGR-02 | K92: 45988 | L92: Access Confirmed Appropriate | M92: =IF(ISBLANK(K92),IF(TODAY()>I92,"OVERDUE - NOT COMPLETED","PENDING - NOT YET DUE"),IF(K92>I92,"COMPLETED LATE","COMPLETED ON TIME")) -> COMPLETED LATE
A93: RC-0092 | B93: E040 | C93: Emma Petrov | D93: SYS-ERP | E93: R03 | F93: Vendor Master Maintenance | G93: Write | H93: 365 | I93: 46079 | J93: MGR-07 | K93: 46064 | L93: Access Confirmed Appropriate | M93: =IF(ISBLANK(K93),IF(TODAY()>I93,"OVERDUE - NOT COMPLETED","PENDING - NOT YET DUE"),IF(K93>I93,"COMPLETED LATE","COMPLETED ON TIME")) -> COMPLETED ON TIME
A94: RC-0093 | B94: E040 | C94: Emma Petrov | D94: SYS-AD | E94: R09 | F94: Standard Network User | G94: Read | H94: 365 | I94: 46246 | J94: MGR-05 | K94: 46244 | L94: Escalated for Review | M94: =IF(ISBLANK(K94),IF(TODAY()>I94,"OVERDUE - NOT COMPLETED","PENDING - NOT YET DUE"),IF(K94>I94,"COMPLETED LATE","COMPLETED ON TIME")) -> COMPLETED ON TIME
A95: RC-0094 | B95: E041 | C95: Emma Dubois | D95: SYS-ERP | E95: R03 | F95: Vendor Master Maintenance | G95: Write | H95: 365 | I95: 46097 | J95: MGR-07 | K95: 46092 | L95: Access Confirmed Appropriate | M95: =IF(ISBLANK(K95),IF(TODAY()>I95,"OVERDUE - NOT COMPLETED","PENDING - NOT YET DUE"),IF(K95>I95,"COMPLETED LATE","COMPLETED ON TIME")) -> COMPLETED ON TIME
A96: RC-0095 | B96: E042 | C96: Carlos Lopez | D96: SYS-ERP | E96: R03 | F96: Vendor Master Maintenance | G96: Write | H96: 365 | I96: 46108 | J96: MGR-05 | K96: 46108 | L96: Access Confirmed Appropriate | M96: =IF(ISBLANK(K96),IF(TODAY()>I96,"OVERDUE - NOT COMPLETED","PENDING - NOT YET DUE"),IF(K96>I96,"COMPLETED LATE","COMPLETED ON TIME")) -> COMPLETED ON TIME
A97: RC-0096 | B97: E042 | C97: Carlos Lopez | D97: SYS-BANK | E97: R13 | F97: Wire Initiation | G97: Write | H97: 365 | I97: 46261 | J97: MGR-05 | K97: 46241 | L97: Access Revoked - No Longer Needed | M97: =IF(ISBLANK(K97),IF(TODAY()>I97,"OVERDUE - NOT COMPLETED","PENDING - NOT YET DUE"),IF(K97>I97,"COMPLETED LATE","COMPLETED ON TIME")) -> COMPLETED ON TIME
A98: RC-0097 | B98: E042 | C98: Carlos Lopez | D98: SYS-BANK | E98: R14 | F98: Wire Approval / Release | G98: Admin | H98: 90 | I98: 46322 | J98: MGR-08 | M98: =IF(ISBLANK(K98),IF(TODAY()>I98,"OVERDUE - NOT COMPLETED","PENDING - NOT YET DUE"),IF(K98>I98,"COMPLETED LATE","COMPLETED ON TIME")) -> PENDING - NOT YET DUE
A99: RC-0098 | B99: E043 | C99: Emma Lopez | D99: SYS-ERP | E99: R05 | F99: GL Journal Approval | G99: Admin | H99: 90 | I99: 46258 | J99: MGR-03 | M99: =IF(ISBLANK(K99),IF(TODAY()>I99,"OVERDUE - NOT COMPLETED","PENDING - NOT YET DUE"),IF(K99>I99,"COMPLETED LATE","COMPLETED ON TIME")) -> OVERDUE - NOT COMPLETED
A100: RC-0099 | B100: E043 | C100: Emma Lopez | D100: SYS-ERP | E100: R01 | F100: AP Invoice Entry | G100: Write | H100: 365 | I100: 46115 | J100: MGR-03 | K100: 46095 | L100: Access Confirmed Appropriate | M100: =IF(ISBLANK(K100),IF(TODAY()>I100,"OVERDUE - NOT COMPLETED","PENDING - NOT YET DUE"),IF(K100>I100,"COMPLETED LATE","COMPLETED ON TIME")) -> COMPLETED ON TIME
A101: RC-0100 | B101: E043 | C101: Emma Lopez | D101: SYS-HRIS | E101: R08 | F101: Employee Master Read-Only | G101: Read | H101: 365 | I101: 46253 | J101: MGR-02 | K101: 46250 | L101: Access Confirmed Appropriate | M101: =IF(ISBLANK(K101),IF(TODAY()>I101,"OVERDUE - NOT COMPLETED","PENDING - NOT YET DUE"),IF(K101>I101,"COMPLETED LATE","COMPLETED ON TIME")) -> COMPLETED ON TIME
A102: RC-0101 | B102: E044 | C102: Hana Andersson | D102: SYS-AD | E102: R10 | F102: Domain Administrator | G102: Admin | H102: 90 | I102: 46194 | J102: MGR-05 | K102: 46180 | L102: Access Confirmed Appropriate | M102: =IF(ISBLANK(K102),IF(TODAY()>I102,"OVERDUE - NOT COMPLETED","PENDING - NOT YET DUE"),IF(K102>I102,"COMPLETED LATE","COMPLETED ON TIME")) -> COMPLETED ON TIME
A103: RC-0102 | B103: E045 | C103: Tariq Santos | D103: SYS-HRIS | E103: R06 | F103: Payroll Data Entry | G103: Write | H103: 365 | I103: 45929 | J103: MGR-05 | K103: 45922 | L103: Access Confirmed Appropriate | M103: =IF(ISBLANK(K103),IF(TODAY()>I103,"OVERDUE - NOT COMPLETED","PENDING - NOT YET DUE"),IF(K103>I103,"COMPLETED LATE","COMPLETED ON TIME")) -> COMPLETED ON TIME
...

Sheet Audit_Testing
A1: GrantID | B1: EmployeeID | C1: EmployeeName | D1: Department | E1: SystemID | F1: RoleID | G1: RoleName | H1: AccessLevel | I1: GrantStatus | J1: GrantDate | K1: TerminationDate | L1: RevokeDate | M1: Test1_Deprovisioning_Flag | N1: ApprovedBy | O1: ApprovalDocRef | P1: Test2_Approval_Flag | Q1: SoD_ConflictRoleID | R1: SoD_ConflictRoleName | S1: Test3_SoD_Flag | T1: Test4_PrivilegedRecert_Flag | U1: Overall_Exception | V1: Exception_RootCause_Category
A2: =Access_Grants!A2 -> AG-0001 | B2: =Access_Grants!B2 -> E001 | C2: =Access_Grants!C2 -> Sophia Chen | D2: =Access_Grants!D2 -> IT Operations | E2: =Access_Grants!E2 -> SYS-AD | F2: =Access_Grants!F2 -> R09 | G2: =Access_Grants!G2 -> Standard Network User | H2: =Access_Grants!H2 -> Read | I2: =Access_Grants!L2 -> Active | J2: =Access_Grants!I2 -> 45031 | K2: =IFERROR(INDEX(HR_Employees!$F$2:$F$51,MATCH(B2,HR_Employees!$A$2:$A$51,0)),"") -> 0 | L2: =IF(Access_Grants!M2="","",Access_Grants!M2) | M2: =IF(K2="","N/A - Active Employee",IF(OR(I2="Active",AND(L2<>"",L2>K2+5)),"EXCEPTION: TERMINATED USER - ACCESS NOT REVOKED TIMELY","OK - Revoked Within SLA")) -> N/A - Active Employee | N2: =Access_Grants!J2&"" -> MGR-02 | O2: =Access_Grants!K2&"" -> CHG-93136 | P2: =IF(OR(TRIM(N2)="",TRIM(O2)=""),"EXCEPTION: NO DOCUMENTED APPROVAL","OK - Approved") -> OK - Approved | Q2: =IFERROR(INDEX(SoD_Conflict_Matrix!$D$2:$D$7,MATCH(F2,SoD_Conflict_Matrix!$B$2:$B$7,0)),IFERROR(INDEX(SoD_Conflict_Matrix!$B$2:$B$7,MATCH(F2,SoD_Conflict_Matrix!$D$2:$D$7,0)),"")) | R2: =IFERROR(INDEX(SoD_Conflict_Matrix!$E$2:$E$7,MATCH(F2,SoD_Conflict_Matrix!$B$2:$B$7,0)),IFERROR(INDEX(SoD_Conflict_Matrix!$C$2:$C$7,MATCH(F2,SoD_Conflict_Matrix!$D$2:$D$7,0)),"")) | S2: =IF(Q2="","No Conflict Rule Applies to This Role",IF(COUNTIFS(Access_Grants!$B$2:$B$175,B2,Access_Grants!$F$2:$F$175,Q2,Access_Grants!$L$2:$L$175,"Active")>0,"EXCEPTION: SoD CONFLICT - ALSO HOLDS "&R2,"OK - No Conflicting Role Held")) -> No Conflict Rule Applies to This Role | T2: =IF(AND(H2="Admin",I2="Active"),IF(COUNTIFS(Recertifications!$B$2:$B$119,B2,Recertifications!$E$2:$E$119,F2,Recertifications!$K$2:$K$119,"<>")>0,"OK - Recertified","EXCEPTION: PRIVILEGED ACCESS NEVER RECERTIFIED"),"N/A - Not Privileged") -> N/A - Not Privileged | U2: =IF(OR(LEFT(M2,9)="EXCEPTION",LEFT(P2,9)="EXCEPTION",LEFT(S2,9)="EXCEPTION",LEFT(T2,9)="EXCEPTION"),"EXCEPTION","Clean") -> Clean | V2: =IF(LEFT(M2,9)="EXCEPTION","Deprovisioning Control Gap",IF(LEFT(S2,9)="EXCEPTION","Segregation of Duties Conflict",IF(LEFT(P2,9)="EXCEPTION","Provisioning Approval Gap",IF(LEFT(T2,9)="EXCEPTION","Recertification Gap","N/A")))) -> N/A
A3: =Access_Grants!A3 -> AG-0002 | B3: =Access_Grants!B3 -> E001 | C3: =Access_Grants!C3 -> Sophia Chen | D3: =Access_Grants!D3 -> IT Operations | E3: =Access_Grants!E3 -> SYS-HRIS | F3: =Access_Grants!F3 -> R08 | G3: =Access_Grants!G3 -> Employee Master Read-Only | H3: =Access_Grants!H3 -> Read | I3: =Access_Grants!L3 -> Active | J3: =Access_Grants!I3 -> 44934 | K3: =IFERROR(INDEX(HR_Employees!$F$2:$F$51,MATCH(B3,HR_Employees!$A$2:$A$51,0)),"") -> 0 | L3: =IF(Access_Grants!M3="","",Access_Grants!M3) | M3: =IF(K3="","N/A - Active Employee",IF(OR(I3="Active",AND(L3<>"",L3>K3+5)),"EXCEPTION: TERMINATED USER - ACCESS NOT REVOKED TIMELY","OK - Revoked Within SLA")) -> N/A - Active Employee | N3: =Access_Grants!J3&"" -> MGR-06 | O3: =Access_Grants!K3&"" -> CHG-27146 | P3: =IF(OR(TRIM(N3)="",TRIM(O3)=""),"EXCEPTION: NO DOCUMENTED APPROVAL","OK - Approved") -> OK - Approved | Q3: =IFERROR(INDEX(SoD_Conflict_Matrix!$D$2:$D$7,MATCH(F3,SoD_Conflict_Matrix!$B$2:$B$7,0)),IFERROR(INDEX(SoD_Conflict_Matrix!$B$2:$B$7,MATCH(F3,SoD_Conflict_Matrix!$D$2:$D$7,0)),"")) | R3: =IFERROR(INDEX(SoD_Conflict_Matrix!$E$2:$E$7,MATCH(F3,SoD_Conflict_Matrix!$B$2:$B$7,0)),IFERROR(INDEX(SoD_Conflict_Matrix!$C$2:$C$7,MATCH(F3,SoD_Conflict_Matrix!$D$2:$D$7,0)),"")) | S3: =IF(Q3="","No Conflict Rule Applies to This Role",IF(COUNTIFS(Access_Grants!$B$2:$B$175,B3,Access_Grants!$F$2:$F$175,Q3,Access_Grants!$L$2:$L$175,"Active")>0,"EXCEPTION: SoD CONFLICT - ALSO HOLDS "&R3,"OK - No Conflicting Role Held")) -> No Conflict Rule Applies to This Role | T3: =IF(AND(H3="Admin",I3="Active"),IF(COUNTIFS(Recertifications!$B$2:$B$119,B3,Recertifications!$E$2:$E$119,F3,Recertifications!$K$2:$K$119,"<>")>0,"OK - Recertified","EXCEPTION: PRIVILEGED ACCESS NEVER RECERTIFIED"),"N/A - Not Privileged") -> N/A - Not Privileged | U3: =IF(OR(LEFT(M3,9)="EXCEPTION",LEFT(P3,9)="EXCEPTION",LEFT(S3,9)="EXCEPTION",LEFT(T3,9)="EXCEPTION"),"EXCEPTION","Clean") -> Clean | V3: =IF(LEFT(M3,9)="EXCEPTION","Deprovisioning Control Gap",IF(LEFT(S3,9)="EXCEPTION","Segregation of Duties Conflict",IF(LEFT(P3,9)="EXCEPTION","Provisioning Approval Gap",IF(LEFT(T3,9)="EXCEPTION","Recertification Gap","N/A")))) -> N/A
A4: =Access_Grants!A4 -> AG-0003 | B4: =Access_Grants!B4 -> E001 | C4: =Access_Grants!C4 -> Sophia Chen | D4: =Access_Grants!D4 -> IT Operations | E4: =Access_Grants!E4 -> SYS-AD | F4: =Access_Grants!F4 -> R10 | G4: =Access_Grants!G4 -> Domain Administrator | H4: =Access_Grants!H4 -> Admin | I4: =Access_Grants!L4 -> Active | J4: =Access_Grants!I4 -> 45831 | K4: =IFERROR(INDEX(HR_Employees!$F$2:$F$51,MATCH(B4,HR_Employees!$A$2:$A$51,0)),"") -> 0 | L4: =IF(Access_Grants!M4="","",Access_Grants!M4) | M4: =IF(K4="","N/A - Active Employee",IF(OR(I4="Active",AND(L4<>"",L4>K4+5)),"EXCEPTION: TERMINATED USER - ACCESS NOT REVOKED TIMELY","OK - Revoked Within SLA")) -> N/A - Active Employee | N4: =Access_Grants!J4&"" -> MGR-09 | O4: =Access_Grants!K4&"" -> CHG-66057 | P4: =IF(OR(TRIM(N4)="",TRIM(O4)=""),"EXCEPTION: NO DOCUMENTED APPROVAL","OK - Approved") -> OK - Approved | Q4: =IFERROR(INDEX(SoD_Conflict_Matrix!$D$2:$D$7,MATCH(F4,SoD_Conflict_Matrix!$B$2:$B$7,0)),IFERROR(INDEX(SoD_Conflict_Matrix!$B$2:$B$7,MATCH(F4,SoD_Conflict_Matrix!$D$2:$D$7,0)),"")) | R4: =IFERROR(INDEX(SoD_Conflict_Matrix!$E$2:$E$7,MATCH(F4,SoD_Conflict_Matrix!$B$2:$B$7,0)),IFERROR(INDEX(SoD_Conflict_Matrix!$C$2:$C$7,MATCH(F4,SoD_Conflict_Matrix!$D$2:$D$7,0)),"")) | S4: =IF(Q4="","No Conflict Rule Applies to This Role",IF(COUNTIFS(Access_Grants!$B$2:$B$175,B4,Access_Grants!$F$2:$F$175,Q4,Access_Grants!$L$2:$L$175,"Active")>0,"EXCEPTION: SoD CONFLICT - ALSO HOLDS "&R4,"OK - No Conflicting Role Held")) -> No Conflict Rule Applies to This Role | T4: =IF(AND(H4="Admin",I4="Active"),IF(COUNTIFS(Recertifications!$B$2:$B$119,B4,Recertifications!$E$2:$E$119,F4,Recertifications!$K$2:$K$119,"<>")>0,"OK - Recertified","EXCEPTION: PRIVILEGED ACCESS NEVER RECERTIFIED"),"N/A - Not Privileged") -> EXCEPTION: PRIVILEGED ACCESS NEVER RECERTIFIED | U4: =IF(OR(LEFT(M4,9)="EXCEPTION",LEFT(P4,9)="EXCEPTION",LEFT(S4,9)="EXCEPTION",LEFT(T4,9)="EXCEPTION"),"EXCEPTION","Clean") -> EXCEPTION | V4: =IF(LEFT(M4,9)="EXCEPTION","Deprovisioning Control Gap",IF(LEFT(S4,9)="EXCEPTION","Segregation of Duties Conflict",IF(LEFT(P4,9)="EXCEPTION","Provisioning Approval Gap",IF(LEFT(T4,9)="EXCEPTION","Recertification Gap","N/A")))) -> Recertification Gap
A5: =Access_Grants!A5 -> AG-0004 | B5: =Access_Grants!B5 -> E002 | C5: =Access_Grants!C5 -> Peter Okafor | D5: =Access_Grants!D5 -> HR | E5: =Access_Grants!E5 -> SYS-AD | F5: =Access_Grants!F5 -> R09 | G5: =Access_Grants!G5 -> Standard Network User | H5: =Access_Grants!H5 -> Read | I5: =Access_Grants!L5 -> Revoked | J5: =Access_Grants!I5 -> 44964 | K5: =IFERROR(INDEX(HR_Employees!$F$2:$F$51,MATCH(B5,HR_Employees!$A$2:$A$51,0)),"") -> 45881 | L5: =IF(Access_Grants!M5="","",Access_Grants!M5) -> 45882 | M5: =IF(K5="","N/A - Active Employee",IF(OR(I5="Active",AND(L5<>"",L5>K5+5)),"EXCEPTION: TERMINATED USER - ACCESS NOT REVOKED TIMELY","OK - Revoked Within SLA")) -> OK - Revoked Within SLA | N5: =Access_Grants!J5&"" | O5: =Access_Grants!K5&"" -> CHG-26704 | P5: =IF(OR(TRIM(N5)="",TRIM(O5)=""),"EXCEPTION: NO DOCUMENTED APPROVAL","OK - Approved") -> EXCEPTION: NO DOCUMENTED APPROVAL | Q5: =IFERROR(INDEX(SoD_Conflict_Matrix!$D$2:$D$7,MATCH(F5,SoD_Conflict_Matrix!$B$2:$B$7,0)),IFERROR(INDEX(SoD_Conflict_Matrix!$B$2:$B$7,MATCH(F5,SoD_Conflict_Matrix!$D$2:$D$7,0)),"")) | R5: =IFERROR(INDEX(SoD_Conflict_Matrix!$E$2:$E$7,MATCH(F5,SoD_Conflict_Matrix!$B$2:$B$7,0)),IFERROR(INDEX(SoD_Conflict_Matrix!$C$2:$C$7,MATCH(F5,SoD_Conflict_Matrix!$D$2:$D$7,0)),"")) | S5: =IF(Q5="","No Conflict Rule Applies to This Role",IF(COUNTIFS(Access_Grants!$B$2:$B$175,B5,Access_Grants!$F$2:$F$175,Q5,Access_Grants!$L$2:$L$175,"Active")>0,"EXCEPTION: SoD CONFLICT - ALSO HOLDS "&R5,"OK - No Conflicting Role Held")) -> No Conflict Rule Applies to This Role | T5: =IF(AND(H5="Admin",I5="Active"),IF(COUNTIFS(Recertifications!$B$2:$B$119,B5,Recertifications!$E$2:$E$119,F5,Recertifications!$K$2:$K$119,"<>")>0,"OK - Recertified","EXCEPTION: PRIVILEGED ACCESS NEVER RECERTIFIED"),"N/A - Not Privileged") -> N/A - Not Privileged | U5: =IF(OR(LEFT(M5,9)="EXCEPTION",LEFT(P5,9)="EXCEPTION",LEFT(S5,9)="EXCEPTION",LEFT(T5,9)="EXCEPTION"),"EXCEPTION","Clean") -> EXCEPTION | V5: =IF(LEFT(M5,9)="EXCEPTION","Deprovisioning Control Gap",IF(LEFT(S5,9)="EXCEPTION","Segregation of Duties Conflict",IF(LEFT(P5,9)="EXCEPTION","Provisioning Approval Gap",IF(LEFT(T5,9)="EXCEPTION","Recertification Gap","N/A")))) -> Provisioning Approval Gap
A6: =Access_Grants!A6 -> AG-0005 | B6: =Access_Grants!B6 -> E002 | C6: =Access_Grants!C6 -> Peter Okafor | D6: =Access_Grants!D6 -> HR | E6: =Access_Grants!E6 -> SYS-HRIS | F6: =Access_Grants!F6 -> R07 | G6: =Access_Grants!G6 -> Payroll Approval / Release | H6: =Access_Grants!H6 -> Admin | I6: =Access_Grants!L6 -> Active | J6: =Access_Grants!I6 -> 45018 | K6: =IFERROR(INDEX(HR_Employees!$F$2:$F$51,MATCH(B6,HR_Employees!$A$2:$A$51,0)),"") -> 45881 | L6: =IF(Access_Grants!M6="","",Access_Grants!M6) | M6: =IF(K6="","N/A - Active Employee",IF(OR(I6="Active",AND(L6<>"",L6>K6+5)),"EXCEPTION: TERMINATED USER - ACCESS NOT REVOKED TIMELY","OK - Revoked Within SLA")) -> EXCEPTION: TERMINATED USER - ACCESS NOT REVOKED TIMELY | N6: =Access_Grants!J6&"" -> MGR-04 | O6: =Access_Grants!K6&"" -> CHG-99399 | P6: =IF(OR(TRIM(N6)="",TRIM(O6)=""),"EXCEPTION: NO DOCUMENTED APPROVAL","OK - Approved") -> OK - Approved | Q6: =IFERROR(INDEX(SoD_Conflict_Matrix!$D$2:$D$7,MATCH(F6,SoD_Conflict_Matrix!$B$2:$B$7,0)),IFERROR(INDEX(SoD_Conflict_Matrix!$B$2:$B$7,MATCH(F6,SoD_Conflict_Matrix!$D$2:$D$7,0)),"")) -> R06 | R6: =IFERROR(INDEX(SoD_Conflict_Matrix!$E$2:$E$7,MATCH(F6,SoD_Conflict_Matrix!$B$2:$B$7,0)),IFERROR(INDEX(SoD_Conflict_Matrix!$C$2:$C$7,MATCH(F6,SoD_Conflict_Matrix!$D$2:$D$7,0)),"")) -> Payroll Data Entry | S6: =IF(Q6="","No Conflict Rule Applies to This Role",IF(COUNTIFS(Access_Grants!$B$2:$B$175,B6,Access_Grants!$F$2:$F$175,Q6,Access_Grants!$L$2:$L$175,"Active")>0,"EXCEPTION: SoD CONFLICT - ALSO HOLDS "&R6,"OK - No Conflicting Role Held")) -> OK - No Conflicting Role Held | T6: =IF(AND(H6="Admin",I6="Active"),IF(COUNTIFS(Recertifications!$B$2:$B$119,B6,Recertifications!$E$2:$E$119,F6,Recertifications!$K$2:$K$119,"<>")>0,"OK - Recertified","EXCEPTION: PRIVILEGED ACCESS NEVER RECERTIFIED"),"N/A - Not Privileged") -> OK - Recertified | U6: =IF(OR(LEFT(M6,9)="EXCEPTION",LEFT(P6,9)="EXCEPTION",LEFT(S6,9)="EXCEPTION",LEFT(T6,9)="EXCEPTION"),"EXCEPTION","Clean") -> EXCEPTION | V6: =IF(LEFT(M6,9)="EXCEPTION","Deprovisioning Control Gap",IF(LEFT(S6,9)="EXCEPTION","Segregation of Duties Conflict",IF(LEFT(P6,9)="EXCEPTION","Provisioning Approval Gap",IF(LEFT(T6,9)="EXCEPTION","Recertification Gap","N/A")))) -> Deprovisioning Control Gap
A7: =Access_Grants!A7 -> AG-0006 | B7: =Access_Grants!B7 -> E002 | C7: =Access_Grants!C7 -> Peter Okafor | D7: =Access_Grants!D7 -> HR | E7: =Access_Grants!E7 -> SYS-HRIS | F7: =Access_Grants!F7 -> R06 | G7: =Access_Grants!G7 -> Payroll Data Entry | H7: =Access_Grants!H7 -> Write | I7: =Access_Grants!L7 -> Revoked | J7: =Access_Grants!I7 -> 45070 | K7: =IFERROR(INDEX(HR_Employees!$F$2:$F$51,MATCH(B7,HR_Employees!$A$2:$A$51,0)),"") -> 45881 | L7: =IF(Access_Grants!M7="","",Access_Grants!M7) -> 45883 | M7: =IF(K7="","N/A - Active Employee",IF(OR(I7="Active",AND(L7<>"",L7>K7+5)),"EXCEPTION: TERMINATED USER - ACCESS NOT REVOKED TIMELY","OK - Revoked Within SLA")) -> OK - Revoked Within SLA | N7: =Access_Grants!J7&"" -> MGR-07 | O7: =Access_Grants!K7&"" -> CHG-91351 | P7: =IF(OR(TRIM(N7)="",TRIM(O7)=""),"EXCEPTION: NO DOCUMENTED APPROVAL","OK - Approved") -> OK - Approved | Q7: =IFERROR(INDEX(SoD_Conflict_Matrix!$D$2:$D$7,MATCH(F7,SoD_Conflict_Matrix!$B$2:$B$7,0)),IFERROR(INDEX(SoD_Conflict_Matrix!$B$2:$B$7,MATCH(F7,SoD_Conflict_Matrix!$D$2:$D$7,0)),"")) -> R07 | R7: =IFERROR(INDEX(SoD_Conflict_Matrix!$E$2:$E$7,MATCH(F7,SoD_Conflict_Matrix!$B$2:$B$7,0)),IFERROR(INDEX(SoD_Conflict_Matrix!$C$2:$C$7,MATCH(F7,SoD_Conflict_Matrix!$D$2:$D$7,0)),"")) -> Payroll Approval / Release | S7: =IF(Q7="","No Conflict Rule Applies to This Role",IF(COUNTIFS(Access_Grants!$B$2:$B$175,B7,Access_Grants!$F$2:$F$175,Q7,Access_Grants!$L$2:$L$175,"Active")>0,"EXCEPTION: SoD CONFLICT - ALSO HOLDS "&R7,"OK - No Conflicting Role Held")) -> EXCEPTION: SoD CONFLICT - ALSO HOLDS Payroll Approval / Release | T7: =IF(AND(H7="Admin",I7="Active"),IF(COUNTIFS(Recertifications!$B$2:$B$119,B7,Recertifications!$E$2:$E$119,F7,Recertifications!$K$2:$K$119,"<>")>0,"OK - Recertified","EXCEPTION: PRIVILEGED ACCESS NEVER RECERTIFIED"),"N/A - Not Privileged") -> N/A - Not Privileged | U7: =IF(OR(LEFT(M7,9)="EXCEPTION",LEFT(P7,9)="EXCEPTION",LEFT(S7,9)="EXCEPTION",LEFT(T7,9)="EXCEPTION"),"EXCEPTION","Clean") -> EXCEPTION | V7: =IF(LEFT(M7,9)="EXCEPTION","Deprovisioning Control Gap",IF(LEFT(S7,9)="EXCEPTION","Segregation of Duties Conflict",IF(LEFT(P7,9)="EXCEPTION","Provisioning Approval Gap",IF(LEFT(T7,9)="EXCEPTION","Recertification Gap","N/A")))) -> Segregation of Duties Conflict
A8: =Access_Grants!A8 -> AG-0007 | B8: =Access_Grants!B8 -> E002 | C8: =Access_Grants!C8 -> Peter Okafor | D8: =Access_Grants!D8 -> HR | E8: =Access_Grants!E8 -> SYS-HRIS | F8: =Access_Grants!F8 -> R08 | G8: =Access_Grants!G8 -> Employee Master Read-Only | H8: =Access_Grants!H8 -> Read | I8: =Access_Grants!L8 -> Active | J8: =Access_Grants!I8 -> 44968 | K8: =IFERROR(INDEX(HR_Employees!$F$2:$F$51,MATCH(B8,HR_Employees!$A$2:$A$51,0)),"") -> 45881 | L8: =IF(Access_Grants!M8="","",Access_Grants!M8) | M8: =IF(K8="","N/A - Active Employee",IF(OR(I8="Active",AND(L8<>"",L8>K8+5)),"EXCEPTION: TERMINATED USER - ACCESS NOT REVOKED TIMELY","OK - Revoked Within SLA")) -> EXCEPTION: TERMINATED USER - ACCESS NOT REVOKED TIMELY | N8: =Access_Grants!J8&"" -> MGR-03 | O8: =Access_Grants!K8&"" | P8: =IF(OR(TRIM(N8)="",TRIM(O8)=""),"EXCEPTION: NO DOCUMENTED APPROVAL","OK - Approved") -> EXCEPTION: NO DOCUMENTED APPROVAL | Q8: =IFERROR(INDEX(SoD_Conflict_Matrix!$D$2:$D$7,MATCH(F8,SoD_Conflict_Matrix!$B$2:$B$7,0)),IFERROR(INDEX(SoD_Conflict_Matrix!$B$2:$B$7,MATCH(F8,SoD_Conflict_Matrix!$D$2:$D$7,0)),"")) | R8: =IFERROR(INDEX(SoD_Conflict_Matrix!$E$2:$E$7,MATCH(F8,SoD_Conflict_Matrix!$B$2:$B$7,0)),IFERROR(INDEX(SoD_Conflict_Matrix!$C$2:$C$7,MATCH(F8,SoD_Conflict_Matrix!$D$2:$D$7,0)),"")) | S8: =IF(Q8="","No Conflict Rule Applies to This Role",IF(COUNTIFS(Access_Grants!$B$2:$B$175,B8,Access_Grants!$F$2:$F$175,Q8,Access_Grants!$L$2:$L$175,"Active")>0,"EXCEPTION: SoD CONFLICT - ALSO HOLDS "&R8,"OK - No Conflicting Role Held")) -> No Conflict Rule Applies to This Role | T8: =IF(AND(H8="Admin",I8="Active"),IF(COUNTIFS(Recertifications!$B$2:$B$119,B8,Recertifications!$E$2:$E$119,F8,Recertifications!$K$2:$K$119,"<>")>0,"OK - Recertified","EXCEPTION: PRIVILEGED ACCESS NEVER RECERTIFIED"),"N/A - Not Privileged") -> N/A - Not Privileged | U8: =IF(OR(LEFT(M8,9)="EXCEPTION",LEFT(P8,9)="EXCEPTION",LEFT(S8,9)="EXCEPTION",LEFT(T8,9)="EXCEPTION"),"EXCEPTION","Clean") -> EXCEPTION | V8: =IF(LEFT(M8,9)="EXCEPTION","Deprovisioning Control Gap",IF(LEFT(S8,9)="EXCEPTION","Segregation of Duties Conflict",IF(LEFT(P8,9)="EXCEPTION","Provisioning Approval Gap",IF(LEFT(T8,9)="EXCEPTION","Recertification Gap","N/A")))) -> Deprovisioning Control Gap
A9: =Access_Grants!A9 -> AG-0008 | B9: =Access_Grants!B9 -> E003 | C9: =Access_Grants!C9 -> Youssef Chen | D9: =Access_Grants!D9 -> Procurement | E9: =Access_Grants!E9 -> SYS-AD | F9: =Access_Grants!F9 -> R09 | G9: =Access_Grants!G9 -> Standard Network User | H9: =Access_Grants!H9 -> Read | I9: =Access_Grants!L9 -> Active | J9: =Access_Grants!I9 -> 45037 | K9: =IFERROR(INDEX(HR_Employees!$F$2:$F$51,MATCH(B9,HR_Employees!$A$2:$A$51,0)),"") -> 0 | L9: =IF(Access_Grants!M9="","",Access_Grants!M9) | M9: =IF(K9="","N/A - Active Employee",IF(OR(I9="Active",AND(L9<>"",L9>K9+5)),"EXCEPTION: TERMINATED USER - ACCESS NOT REVOKED TIMELY","OK - Revoked Within SLA")) -> N/A - Active Employee | N9: =Access_Grants!J9&"" -> MGR-07 | O9: =Access_Grants!K9&"" -> CHG-15075 | P9: =IF(OR(TRIM(N9)="",TRIM(O9)=""),"EXCEPTION: NO DOCUMENTED APPROVAL","OK - Approved") -> OK - Approved | Q9: =IFERROR(INDEX(SoD_Conflict_Matrix!$D$2:$D$7,MATCH(F9,SoD_Conflict_Matrix!$B$2:$B$7,0)),IFERROR(INDEX(SoD_Conflict_Matrix!$B$2:$B$7,MATCH(F9,SoD_Conflict_Matrix!$D$2:$D$7,0)),"")) | R9: =IFERROR(INDEX(SoD_Conflict_Matrix!$E$2:$E$7,MATCH(F9,SoD_Conflict_Matrix!$B$2:$B$7,0)),IFERROR(INDEX(SoD_Conflict_Matrix!$C$2:$C$7,MATCH(F9,SoD_Conflict_Matrix!$D$2:$D$7,0)),"")) | S9: =IF(Q9="","No Conflict Rule Applies to This Role",IF(COUNTIFS(Access_Grants!$B$2:$B$175,B9,Access_Grants!$F$2:$F$175,Q9,Access_Grants!$L$2:$L$175,"Active")>0,"EXCEPTION: SoD CONFLICT - ALSO HOLDS "&R9,"OK - No Conflicting Role Held")) -> No Conflict Rule Applies to This Role | T9: =IF(AND(H9="Admin",I9="Active"),IF(COUNTIFS(Recertifications!$B$2:$B$119,B9,Recertifications!$E$2:$E$119,F9,Recertifications!$K$2:$K$119,"<>")>0,"OK - Recertified","EXCEPTION: PRIVILEGED ACCESS NEVER RECERTIFIED"),"N/A - Not Privileged") -> N/A - Not Privileged | U9: =IF(OR(LEFT(M9,9)="EXCEPTION",LEFT(P9,9)="EXCEPTION",LEFT(S9,9)="EXCEPTION",LEFT(T9,9)="EXCEPTION"),"EXCEPTION","Clean") -> Clean | V9: =IF(LEFT(M9,9)="EXCEPTION","Deprovisioning Control Gap",IF(LEFT(S9,9)="EXCEPTION","Segregation of Duties Conflict",IF(LEFT(P9,9)="EXCEPTION","Provisioning Approval Gap",IF(LEFT(T9,9)="EXCEPTION","Recertification Gap","N/A")))) -> N/A
A10: =Access_Grants!A10 -> AG-0009 | B10: =Access_Grants!B10 -> E003 | C10: =Access_Grants!C10 -> Youssef Chen | D10: =Access_Grants!D10 -> Procurement | E10: =Access_Grants!E10 -> SYS-ERP | F10: =Access_Grants!F10 -> R03 | G10: =Access_Grants!G10 -> Vendor Master Maintenance | H10: =Access_Grants!H10 -> Write | I10: =Access_Grants!L10 -> Active | J10: =Access_Grants!I10 -> 45763 | K10: =IFERROR(INDEX(HR_Employees!$F$2:$F$51,MATCH(B10,HR_Employees!$A$2:$A$51,0)),"") -> 0 | L10: =IF(Access_Grants!M10="","",Access_Grants!M10) | M10: =IF(K10="","N/A - Active Employee",IF(OR(I10="Active",AND(L10<>"",L10>K10+5)),"EXCEPTION: TERMINATED USER - ACCESS NOT REVOKED TIMELY","OK - Revoked Within SLA")) -> N/A - Active Employee | N10: =Access_Grants!J10&"" -> MGR-08 | O10: =Access_Grants!K10&"" -> CHG-55830 | P10: =IF(OR(TRIM(N10)="",TRIM(O10)=""),"EXCEPTION: NO DOCUMENTED APPROVAL","OK - Approved") -> OK - Approved | Q10: =IFERROR(INDEX(SoD_Conflict_Matrix!$D$2:$D$7,MATCH(F10,SoD_Conflict_Matrix!$B$2:$B$7,0)),IFERROR(INDEX(SoD_Conflict_Matrix!$B$2:$B$7,MATCH(F10,SoD_Conflict_Matrix!$D$2:$D$7,0)),"")) -> R02 | R10: =IFERROR(INDEX(SoD_Conflict_Matrix!$E$2:$E$7,MATCH(F10,SoD_Conflict_Matrix!$B$2:$B$7,0)),IFERROR(INDEX(SoD_Conflict_Matrix!$C$2:$C$7,MATCH(F10,SoD_Conflict_Matrix!$D$2:$D$7,0)),"")) -> AP Payment Approval | S10: =IF(Q10="","No Conflict Rule Applies to This Role",IF(COUNTIFS(Access_Grants!$B$2:$B$175,B10,Access_Grants!$F$2:$F$175,Q10,Access_Grants!$L$2:$L$175,"Active")>0,"EXCEPTION: SoD CONFLICT - ALSO HOLDS "&R10,"OK - No Conflicting Role Held")) -> OK - No Conflicting Role Held | T10: =IF(AND(H10="Admin",I10="Active"),IF(COUNTIFS(Recertifications!$B$2:$B$119,B10,Recertifications!$E$2:$E$119,F10,Recertifications!$K$2:$K$119,"<>")>0,"OK - Recertified","EXCEPTION: PRIVILEGED ACCESS NEVER RECERTIFIED"),"N/A - Not Privileged") -> N/A - Not Privileged | U10: =IF(OR(LEFT(M10,9)="EXCEPTION",LEFT(P10,9)="EXCEPTION",LEFT(S10,9)="EXCEPTION",LEFT(T10,9)="EXCEPTION"),"EXCEPTION","Clean") -> Clean | V10: =IF(LEFT(M10,9)="EXCEPTION","Deprovisioning Control Gap",IF(LEFT(S10,9)="EXCEPTION","Segregation of Duties Conflict",IF(LEFT(P10,9)="EXCEPTION","Provisioning Approval Gap",IF(LEFT(T10,9)="EXCEPTION","Recertification Gap","N/A")))) -> N/A
A11: =Access_Grants!A11 -> AG-0010 | B11: =Access_Grants!B11 -> E003 | C11: =Access_Grants!C11 -> Youssef Chen | D11: =Access_Grants!D11 -> Procurement | E11: =Access_Grants!E11 -> SYS-ERP | F11: =Access_Grants!F11 -> R01 | G11: =Access_Grants!G11 -> AP Invoice Entry | H11: =Access_Grants!H11 -> Write | I11: =Access_Grants!L11 -> Active | J11: =Access_Grants!I11 -> 45160 | K11: =IFERROR(INDEX(HR_Employees!$F$2:$F$51,MATCH(B11,HR_Employees!$A$2:$A$51,0)),"") -> 0 | L11: =IF(Access_Grants!M11="","",Access_Grants!M11) | M11: =IF(K11="","N/A - Active Employee",IF(OR(I11="Active",AND(L11<>"",L11>K11+5)),"EXCEPTION: TERMINATED USER - ACCESS NOT REVOKED TIMELY","OK - Revoked Within SLA")) -> N/A - Active Employee | N11: =Access_Grants!J11&"" -> MGR-04 | O11: =Access_Grants!K11&"" -> CHG-13101 | P11: =IF(OR(TRIM(N11)="",TRIM(O11)=""),"EXCEPTION: NO DOCUMENTED APPROVAL","OK - Approved") -> OK - Approved | Q11: =IFERROR(INDEX(SoD_Conflict_Matrix!$D$2:$D$7,MATCH(F11,SoD_Conflict_Matrix!$B$2:$B$7,0)),IFERROR(INDEX(SoD_Conflict_Matrix!$B$2:$B$7,MATCH(F11,SoD_Conflict_Matrix!$D$2:$D$7,0)),"")) -> R02 | R11: =IFERROR(INDEX(SoD_Conflict_Matrix!$E$2:$E$7,MATCH(F11,SoD_Conflict_Matrix!$B$2:$B$7,0)),IFERROR(INDEX(SoD_Conflict_Matrix!$C$2:$C$7,MATCH(F11,SoD_Conflict_Matrix!$D$2:$D$7,0)),"")) -> AP Payment Approval | S11: =IF(Q11="","No Conflict Rule Applies to This Role",IF(COUNTIFS(Access_Grants!$B$2:$B$175,B11,Access_Grants!$F$2:$F$175,Q11,Access_Grants!$L$2:$L$175,"Active")>0,"EXCEPTION: SoD CONFLICT - ALSO HOLDS "&R11,"OK - No Conflicting Role Held")) -> OK - No Conflicting Role Held | T11: =IF(AND(H11="Admin",I11="Active"),IF(COUNTIFS(Recertifications!$B$2:$B$119,B11,Recertifications!$E$2:$E$119,F11,Recertifications!$K$2:$K$119,"<>")>0,"OK - Recertified","EXCEPTION: PRIVILEGED ACCESS NEVER RECERTIFIED"),"N/A - Not Privileged") -> N/A - Not Privileged | U11: =IF(OR(LEFT(M11,9)="EXCEPTION",LEFT(P11,9)="EXCEPTION",LEFT(S11,9)="EXCEPTION",LEFT(T11,9)="EXCEPTION"),"EXCEPTION","Clean") -> Clean | V11: =IF(LEFT(M11,9)="EXCEPTION","Deprovisioning Control Gap",IF(LEFT(S11,9)="EXCEPTION","Segregation of Duties Conflict",IF(LEFT(P11,9)="EXCEPTION","Provisioning Approval Gap",IF(LEFT(T11,9)="EXCEPTION","Recertification Gap","N/A")))) -> N/A
A12: =Access_Grants!A12 -> AG-0011 | B12: =Access_Grants!B12 -> E004 | C12: =Access_Grants!C12 -> Omar Khan | D12: =Access_Grants!D12 -> IT Operations | E12: =Access_Grants!E12 -> SYS-AD | F12: =Access_Grants!F12 -> R10 | G12: =Access_Grants!G12 -> Domain Administrator | H12: =Access_Grants!H12 -> Admin | I12: =Access_Grants!L12 -> Revoked | J12: =Access_Grants!I12 -> 44978 | K12: =IFERROR(INDEX(HR_Employees!$F$2:$F$51,MATCH(B12,HR_Employees!$A$2:$A$51,0)),"") -> 0 | L12: =IF(Access_Grants!M12="","",Access_Grants!M12) -> 45512 | M12: =IF(K12="","N/A - Active Employee",IF(OR(I12="Active",AND(L12<>"",L12>K12+5)),"EXCEPTION: TERMINATED USER - ACCESS NOT REVOKED TIMELY","OK - Revoked Within SLA")) -> N/A - Active Employee | N12: =Access_Grants!J12&"" -> System Auto-Provision | O12: =Access_Grants!K12&"" -> CHG-80282 | P12: =IF(OR(TRIM(N12)="",TRIM(O12)=""),"EXCEPTION: NO DOCUMENTED APPROVAL","OK - Approved") -> OK - Approved | Q12: =IFERROR(INDEX(SoD_Conflict_Matrix!$D$2:$D$7,MATCH(F12,SoD_Conflict_Matrix!$B$2:$B$7,0)),IFERROR(INDEX(SoD_Conflict_Matrix!$B$2:$B$7,MATCH(F12,SoD_Conflict_Matrix!$D$2:$D$7,0)),"")) | R12: =IFERROR(INDEX(SoD_Conflict_Matrix!$E$2:$E$7,MATCH(F12,SoD_Conflict_Matrix!$B$2:$B$7,0)),IFERROR(INDEX(SoD_Conflict_Matrix!$C$2:$C$7,MATCH(F12,SoD_Conflict_Matrix!$D$2:$D$7,0)),"")) | S12: =IF(Q12="","No Conflict Rule Applies to This Role",IF(COUNTIFS(Access_Grants!$B$2:$B$175,B12,Access_Grants!$F$2:$F$175,Q12,Access_Grants!$L$2:$L$175,"Active")>0,"EXCEPTION: SoD CONFLICT - ALSO HOLDS "&R12,"OK - No Conflicting Role Held")) -> No Conflict Rule Applies to This Role | T12: =IF(AND(H12="Admin",I12="Active"),IF(COUNTIFS(Recertifications!$B$2:$B$119,B12,Recertifications!$E$2:$E$119,F12,Recertifications!$K$2:$K$119,"<>")>0,"OK - Recertified","EXCEPTION: PRIVILEGED ACCESS NEVER RECERTIFIED"),"N/A - Not Privileged") -> N/A - Not Privileged | U12: =IF(OR(LEFT(M12,9)="EXCEPTION",LEFT(P12,9)="EXCEPTION",LEFT(S12,9)="EXCEPTION",LEFT(T12,9)="EXCEPTION"),"EXCEPTION","Clean") -> Clean | V12: =IF(LEFT(M12,9)="EXCEPTION","Deprovisioning Control Gap",IF(LEFT(S12,9)="EXCEPTION","Segregation of Duties Conflict",IF(LEFT(P12,9)="EXCEPTION","Provisioning Approval Gap",IF(LEFT(T12,9)="EXCEPTION","Recertification Gap","N/A")))) -> N/A
A13: =Access_Grants!A13 -> AG-0012 | B13: =Access_Grants!B13 -> E004 | C13: =Access_Grants!C13 -> Omar Khan | D13: =Access_Grants!D13 -> IT Operations | E13: =Access_Grants!E13 -> SYS-HRIS | F13: =Access_Grants!F13 -> R08 | G13: =Access_Grants!G13 -> Employee Master Read-Only | H13: =Access_Grants!H13 -> Read | I13: =Access_Grants!L13 -> Active | J13: =Access_Grants!I13 -> 44949 | K13: =IFERROR(INDEX(HR_Employees!$F$2:$F$51,MATCH(B13,HR_Employees!$A$2:$A$51,0)),"") -> 0 | L13: =IF(Access_Grants!M13="","",Access_Grants!M13) | M13: =IF(K13="","N/A - Active Employee",IF(OR(I13="Active",AND(L13<>"",L13>K13+5)),"EXCEPTION: TERMINATED USER - ACCESS NOT REVOKED TIMELY","OK - Revoked Within SLA")) -> N/A - Active Employee | N13: =Access_Grants!J13&"" -> MGR-10 | O13: =Access_Grants!K13&"" | P13: =IF(OR(TRIM(N13)="",TRIM(O13)=""),"EXCEPTION: NO DOCUMENTED APPROVAL","OK - Approved") -> EXCEPTION: NO DOCUMENTED APPROVAL | Q13: =IFERROR(INDEX(SoD_Conflict_Matrix!$D$2:$D$7,MATCH(F13,SoD_Conflict_Matrix!$B$2:$B$7,0)),IFERROR(INDEX(SoD_Conflict_Matrix!$B$2:$B$7,MATCH(F13,SoD_Conflict_Matrix!$D$2:$D$7,0)),"")) | R13: =IFERROR(INDEX(SoD_Conflict_Matrix!$E$2:$E$7,MATCH(F13,SoD_Conflict_Matrix!$B$2:$B$7,0)),IFERROR(INDEX(SoD_Conflict_Matrix!$C$2:$C$7,MATCH(F13,SoD_Conflict_Matrix!$D$2:$D$7,0)),"")) | S13: =IF(Q13="","No Conflict Rule Applies to This Role",IF(COUNTIFS(Access_Grants!$B$2:$B$175,B13,Access_Grants!$F$2:$F$175,Q13,Access_Grants!$L$2:$L$175,"Active")>0,"EXCEPTION: SoD CONFLICT - ALSO HOLDS "&R13,"OK - No Conflicting Role Held")) -> No Conflict Rule Applies to This Role | T13: =IF(AND(H13="Admin",I13="Active"),IF(COUNTIFS(Recertifications!$B$2:$B$119,B13,Recertifications!$E$2:$E$119,F13,Recertifications!$K$2:$K$119,"<>")>0,"OK - Recertified","EXCEPTION: PRIVILEGED ACCESS NEVER RECERTIFIED"),"N/A - Not Privileged") -> N/A - Not Privileged | U13: =IF(OR(LEFT(M13,9)="EXCEPTION",LEFT(P13,9)="EXCEPTION",LEFT(S13,9)="EXCEPTION",LEFT(T13,9)="EXCEPTION"),"EXCEPTION","Clean") -> EXCEPTION | V13: =IF(LEFT(M13,9)="EXCEPTION","Deprovisioning Control Gap",IF(LEFT(S13,9)="EXCEPTION","Segregation of Duties Conflict",IF(LEFT(P13,9)="EXCEPTION","Provisioning Approval Gap",IF(LEFT(T13,9)="EXCEPTION","Recertification Gap","N/A")))) -> Provisioning Approval Gap
... A175: =Access_Grants!A175 -> AG-0174 | B175: =Access_Grants!B175 -> E050 | C175: =Access_Grants!C175 -> Ana Silva | D175: =Access_Grants!D175 -> IT Operations | E175: =Access_Grants!E175 -> SYS-HRIS | F175: =Access_Grants!F175 -> R08 | G175: =Access_Grants!G175 -> Employee Master Read-Only | H175: =Access_Grants!H175 -> Read | I175: =Access_Grants!L175 -> Active | J175: =Access_Grants!I175 -> 45506 | K175: =IFERROR(INDEX(HR_Employees!$F$2:$F$51,MATCH(B175,HR_Employees!$A$2:$A$51,0)),"") -> 0 | L175: =IF(Access_Grants!M175="","",Access_Grants!M175) | M175: =IF(K175="","N/A - Active Employee",IF(OR(I175="Active",AND(L175<>"",L175>K175+5)),"EXCEPTION: TERMINATED USER - ACCESS NOT REVOKED TIMELY","OK - Revoked Within SLA")) -> N/A - Active Employee | N175: =Access_Grants!J175&"" -> MGR-07 | O175: =Access_Grants!K175&"" -> CHG-63578 | P175: =IF(OR(TRIM(N175)="",TRIM(O175)=""),"EXCEPTION: NO DOCUMENTED APPROVAL","OK - Approved") -> OK - Approved | Q175: =IFERROR(INDEX(SoD_Conflict_Matrix!$D$2:$D$7,MATCH(F175,SoD_Conflict_Matrix!$B$2:$B$7,0)),IFERROR(INDEX(SoD_Conflict_Matrix!$B$2:$B$7,MATCH(F175,SoD_Conflict_Matrix!$D$2:$D$7,0)),"")) | R175: =IFERROR(INDEX(SoD_Conflict_Matrix!$E$2:$E$7,MATCH(F175,SoD_Conflict_Matrix!$B$2:$B$7,0)),IFERROR(INDEX(SoD_Conflict_Matrix!$C$2:$C$7,MATCH(F175,SoD_Conflict_Matrix!$D$2:$D$7,0)),"")) | S175: =IF(Q175="","No Conflict Rule Applies to This Role",IF(COUNTIFS(Access_Grants!$B$2:$B$175,B175,Access_Grants!$F$2:$F$175,Q175,Access_Grants!$L$2:$L$175,"Active")>0,"EXCEPTION: SoD CONFLICT - ALSO HOLDS "&R175,"OK - No Conflicting Role Held")) -> No Conflict Rule Applies to This Role | T175: =IF(AND(H175="Admin",I175="Active"),IF(COUNTIFS(Recertifications!$B$2:$B$119,B175,Recertifications!$E$2:$E$119,F175,Recertifications!$K$2:$K$119,"<>")>0,"OK - Recertified","EXCEPTION: PRIVILEGED ACCESS NEVER RECERTIFIED"),"N/A - Not Privileged") -> N/A - Not Privileged | U175: =IF(OR(LEFT(M175,9)="EXCEPTION",LEFT(P175,9)="EXCEPTION",LEFT(S175,9)="EXCEPTION",LEFT(T175,9)="EXCEPTION"),"EXCEPTION","Clean") -> Clean | V175: =IF(LEFT(M175,9)="EXCEPTION","Deprovisioning Control Gap",IF(LEFT(S175,9)="EXCEPTION","Segregation of Duties Conflict",IF(LEFT(P175,9)="EXCEPTION","Provisioning Approval Gap",IF(LEFT(T175,9)="EXCEPTION","Recertification Gap","N/A")))) -> N/A

Sheet Dashboard
B2: ITGC Access Audit — Exception Dashboard
B3: All figures below are COUNTIFS/SUMPRODUCT formulas reading live from Audit_Testing and Recertifications — refresh by recalculating the workbook. Audit_Testing is a proper Excel Table ('AuditTesting'), so a native PivotTable can also be inserted from it at any time.
B5: Total Access Grants Tested | E5: Total Exceptions | H5: Overall Exception Rate | K5: Privileged (Admin) Grants
B6: =COUNTA(AuditTesting[GrantID]) -> 174 | E6: =COUNTIF(AuditTesting[Overall_Exception],"EXCEPTION") -> 78 | H6: =E6/B6 -> 0.44827586 | K6: =COUNTIF(AuditTesting[AccessLevel],"Admin") -> 30
B9: Exception Rate by Department | G9: Exception Rate by System
B10: Department | C10: Total Grants | D10: Exceptions | E10: Exception Rate | G10: System | H10: Total Grants | I10: Exceptions | J10: Exception Rate
B11: Accounts Payable | C11: =COUNTIF(AuditTesting[Department],B11) -> 27 | D11: =COUNTIFS(AuditTesting[Department],B11,AuditTesting[Overall_Exception],"EXCEPTION") -> 16 | E11: =IF(C11=0,0,D11/C11) -> 0.59259259 | G11: SYS-ERP — ERP Finance (SAP) | H11: =COUNTIF(AuditTesting[SystemID],"SYS-ERP") -> 53 | I11: =COUNTIFS(AuditTesting[SystemID],"SYS-ERP",AuditTesting[Overall_Exception],"EXCEPTION") -> 27 | J11: =IF(H11=0,0,I11/H11) -> 0.50943396
B12: Customer Service | C12: =COUNTIF(AuditTesting[Department],B12) -> 16 | D12: =COUNTIFS(AuditTesting[Department],B12,AuditTesting[Overall_Exception],"EXCEPTION") -> 5 | E12: =IF(C12=0,0,D12/C12) -> 0.3125 | G12: SYS-HRIS — HRIS / Payroll | H12: =COUNTIF(AuditTesting[SystemID],"SYS-HRIS") -> 53 | I12: =COUNTIFS(AuditTesting[SystemID],"SYS-HRIS",AuditTesting[Overall_Exception],"EXCEPTION") -> 26 | J12: =IF(H12=0,0,I12/H12) -> 0.49056604
B13: Finance | C13: =COUNTIF(AuditTesting[Department],B13) -> 15 | D13: =COUNTIFS(AuditTesting[Department],B13,AuditTesting[Overall_Exception],"EXCEPTION") -> 5 | E13: =IF(C13=0,0,D13/C13) -> 0.33333333 | G13: SYS-AD — Active Directory / Network | H13: =COUNTIF(AuditTesting[SystemID],"SYS-AD") -> 48 | I13: =COUNTIFS(AuditTesting[SystemID],"SYS-AD",AuditTesting[Overall_Exception],"EXCEPTION") -> 10 | J13: =IF(H13=0,0,I13/H13) -> 0.20833333
B14: HR | C14: =COUNTIF(AuditTesting[Department],B14) -> 21 | D14: =COUNTIFS(AuditTesting[Department],B14,AuditTesting[Overall_Exception],"EXCEPTION") -> 12 | E14: =IF(C14=0,0,D14/C14) -> 0.57142857 | G14: SYS-CRM — CRM Sales | H14: =COUNTIF(AuditTesting[SystemID],"SYS-CRM") -> 4 | I14: =COUNTIFS(AuditTesting[SystemID],"SYS-CRM",AuditTesting[Overall_Exception],"EXCEPTION") -> 0 | J14: =IF(H14=0,0,I14/H14) -> 0
B15: IT Operations | C15: =COUNTIF(AuditTesting[Department],B15) -> 26 | D15: =COUNTIFS(AuditTesting[Department],B15,AuditTesting[Overall_Exception],"EXCEPTION") -> 8 | E15: =IF(C15=0,0,D15/C15) -> 0.30769231 | G15: SYS-BANK — Banking Portal | H15: =COUNTIF(AuditTesting[SystemID],"SYS-BANK") -> 16 | I15: =COUNTIFS(AuditTesting[SystemID],"SYS-BANK",AuditTesting[Overall_Exception],"EXCEPTION") -> 15 | J15: =IF(H15=0,0,I15/H15) -> 0.9375
B16: Payroll | C16: =COUNTIF(AuditTesting[Department],B16) -> 8 | D16: =COUNTIFS(AuditTesting[Department],B16,AuditTesting[Overall_Exception],"EXCEPTION") -> 6 | E16: =IF(C16=0,0,D16/C16) -> 0.75
B17: Procurement | C17: =COUNTIF(AuditTesting[Department],B17) -> 42 | D17: =COUNTIFS(AuditTesting[Department],B17,AuditTesting[Overall_Exception],"EXCEPTION") -> 14 | E17: =IF(C17=0,0,D17/C17) -> 0.33333333
B18: Treasury | C18: =COUNTIF(AuditTesting[Department],B18) -> 19 | D18: =COUNTIFS(AuditTesting[Department],B18,AuditTesting[Overall_Exception],"EXCEPTION") -> 12 | E18: =IF(C18=0,0,D18/C18) -> 0.63157895
B21: Recertification Timeliness by Reviewer | G21: Exceptions by Root-Cause Category
B22: Reviewer | C22: Assigned Recerts | D22: Overdue / Completed Late | E22: % Overdue or Late | G22: Root-Cause Category | H22: Count | I22: % of Total Exceptions
B23: MGR-01 | C23: =COUNTIF(RecertLog[Reviewer],B23) -> 7 | D23: =COUNTIFS(RecertLog[Reviewer],B23,RecertLog[Recert_Status],"OVERDUE - NOT COMPLETED")+COUNTIFS(RecertLog[Reviewer],B23,RecertLog[Recert_Status],"COMPLETED LATE") -> 2 | E23: =IF(C23=0,0,D23/C23) -> 0.28571429 | G23: Deprovisioning Control Gap | H23: =COUNTIF(AuditTesting[Exception_RootCause_Category],G23) -> 15 | I23: =IF($E$6=0,0,H23/$E$6) -> 0.19230769
B24: MGR-02 | C24: =COUNTIF(RecertLog[Reviewer],B24) -> 10 | D24: =COUNTIFS(RecertLog[Reviewer],B24,RecertLog[Recert_Status],"OVERDUE - NOT COMPLETED")+COUNTIFS(RecertLog[Reviewer],B24,RecertLog[Recert_Status],"COMPLETED LATE") -> 2 | E24: =IF(C24=0,0,D24/C24) -> 0.2 | G24: Segregation of Duties Conflict | H24: =COUNTIF(AuditTesting[Exception_RootCause_Category],G24) -> 45 | I24: =IF($E$6=0,0,H24/$E$6) -> 0.57692308
B25: MGR-03 | C25: =COUNTIF(RecertLog[Reviewer],B25) -> 17 | D25: =COUNTIFS(RecertLog[Reviewer],B25,RecertLog[Recert_Status],"OVERDUE - NOT COMPLETED")+COUNTIFS(RecertLog[Reviewer],B25,RecertLog[Recert_Status],"COMPLETED LATE") -> 3 | E25: =IF(C25=0,0,D25/C25) -> 0.17647059 | G25: Provisioning Approval Gap | H25: =COUNTIF(AuditTesting[Exception_RootCause_Category],G25) -> 15 | I25: =IF($E$6=0,0,H25/$E$6) -> 0.19230769
B26: MGR-04 | C26: =COUNTIF(RecertLog[Reviewer],B26) -> 7 | D26: =COUNTIFS(RecertLog[Reviewer],B26,RecertLog[Recert_Status],"OVERDUE - NOT COMPLETED")+COUNTIFS(RecertLog[Reviewer],B26,RecertLog[Recert_Status],"COMPLETED LATE") -> 1 | E26: =IF(C26=0,0,D26/C26) -> 0.14285714 | G26: Recertification Gap | H26: =COUNTIF(AuditTesting[Exception_RootCause_Category],G26) -> 3 | I26: =IF($E$6=0,0,H26/$E$6) -> 0.038461538
B27: MGR-05 | C27: =COUNTIF(RecertLog[Reviewer],B27) -> 14 | D27: =COUNTIFS(RecertLog[Reviewer],B27,RecertLog[Recert_Status],"OVERDUE - NOT COMPLETED")+COUNTIFS(RecertLog[Reviewer],B27,RecertLog[Recert_Status],"COMPLETED LATE") -> 5 | E27: =IF(C27=0,0,D27/C27) -> 0.35714286
B28: MGR-06 | C28: =COUNTIF(RecertLog[Reviewer],B28) -> 17 | D28: =COUNTIFS(RecertLog[Reviewer],B28,RecertLog[Recert_Status],"OVERDUE - NOT COMPLETED")+COUNTIFS(RecertLog[Reviewer],B28,RecertLog[Recert_Status],"COMPLETED LATE") -> 1 | E28: =IF(C28=0,0,D28/C28) -> 0.058823529
B29: MGR-07 | C29: =COUNTIF(RecertLog[Reviewer],B29) -> 14 | D29: =COUNTIFS(RecertLog[Reviewer],B29,RecertLog[Recert_Status],"OVERDUE - NOT COMPLETED")+COUNTIFS(RecertLog[Reviewer],B29,RecertLog[Recert_Status],"COMPLETED LATE") -> 3 | E29: =IF(C29=0,0,D29/C29) -> 0.21428571
B30: MGR-08 | C30: =COUNTIF(RecertLog[Reviewer],B30) -> 12 | D30: =COUNTIFS(RecertLog[Reviewer],B30,RecertLog[Recert_Status],"OVERDUE - NOT COMPLETED")+COUNTIFS(RecertLog[Reviewer],B30,RecertLog[Recert_Status],"COMPLETED LATE") -> 3 | E30: =IF(C30=0,0,D30/C30) -> 0.25
B31: MGR-09 | C31: =COUNTIF(RecertLog[Reviewer],B31) -> 11 | D31: =COUNTIFS(RecertLog[Reviewer],B31,RecertLog[Recert_Status],"OVERDUE - NOT COMPLETED")+COUNTIFS(RecertLog[Reviewer],B31,RecertLog[Recert_Status],"COMPLETED LATE") -> 2 | E31: =IF(C31=0,0,D31/C31) -> 0.18181818
B32: MGR-10 | C32: =COUNTIF(RecertLog[Reviewer],B32) -> 9 | D32: =COUNTIFS(RecertLog[Reviewer],B32,RecertLog[Recert_Status],"OVERDUE - NOT COMPLETED")+COUNTIFS(RecertLog[Reviewer],B32,RecertLog[Recert_Status],"COMPLETED LATE") -> 3 | E32: =IF(C32=0,0,D32/C32) -> 0.33333333

Sheet Findings_Memo
B2: MEMORANDUM
B4: To: | C4: Audit Committee; CIO; VP, Information Security
B5: From: | C5: Internal Audit — IT General Controls
B6: Date: | C6: September 18, 2026
B7: Re: | C7: User Access Provisioning, SoD, and Recertification Audit — FY2026 Q3
B9: Objective & Scope
B10: Internal Audit performed a review of IT general controls (ITGC) over user access for five in-scope financial and operational systems: ERP Finance, HRIS/Payroll, Active Directory, CRM Sales, and the Banking Portal. The review tested 174 active and historical access grants across 50 employees against four control objectives: (1) timely deprovisioning of terminated users, (2) segregation of duties (SoD) between conflicting roles, (3) documented approval prior to provisioning, and (4) periodic recertification of access, with emphasis on privileged/administrative entitlements.
B12: Methodology
B13: Access, HR termination, and recertification logs were reconciled using formula-based testing (INDEX/MATCH, COUNTIFS, nested IF/AND/OR) rather than manual sampling — every one of the 174 grants in population was tested against all four control objectives (see Audit_Testing tab), not a sample. Company policy (per IT Access Management Standard) requires: access revoked within 5 calendar days of termination; no user to concurrently hold two roles listed in the SoD conflict matrix (6 rules tested, see SoD_Conflict_Matrix tab); every grant to carry a named approver and change-ticket reference; and privileged/admin access to be recertified at least every 90 days (all other access annually).
B15: Overall Result
B16: 78 of 174 access grants tested (44.8%) triggered at least one control exception. Exception rates were materially higher in Accounts Payable (59.3%), Payroll (75.0%) and Treasury (63.2%) than in IT Operations (30.8%) or Customer Service (31.3%), and were concentrated in the ERP Finance, HRIS/Payroll and Banking Portal systems — the three systems with the most direct path to financial-statement or cash impact. This pattern indicates the control gaps are not evenly distributed noise but are concentrated in the highest financial-risk systems, and should be prioritized accordingly.
B18: Detailed Findings
B20: Finding 1: Segregation of Duties Conflicts (45 exceptions — HIGH)
B21: Condition (what we found):
B22: 45 access grants (across 12 employees) show a single identity concurrently holding two roles defined as conflicting in the SoD matrix — most frequently AP Invoice Entry + AP Payment Approval, and Wire Initiation + Wire Approval/Release.
B23: Criteria (what should happen):
B24: IT Access Management Standard §4.2 prohibits any single user from holding both roles in a defined SoD pair without a documented compensating control (e.g., independent monthly review).
... B69: Controls over user access provisioning, segregation of duties, and periodic recertification are assessed as PARTIALLY EFFECTIVE. Detective capability exists (this testing itself proves the population is fully reconcilable), but key preventive controls — an automated HRIS-to-IAM deprovisioning feed and a preventive SoD check at the point of request — are absent, resulting in a 44.8% exception rate concentrated in financially significant systems. Internal Audit recommends management formally track remediation of the four findings above with target dates, and that this Audit_Testing workbook (or an equivalent automated control) be re-run monthly as an interim detective control while preventive automation is implemented.
